{
"meta":{"test_sets":[],"test_metrics":[],"learn_metrics":[{"best_value":"Min","name":"RMSE"}],"launch_mode":"Train","parameters":"","iteration_count":1000,"learn_sets":["learn"],"name":"experiment"},
"iterations":[
{"learn":[14.59871775],"iteration":0,"passed_time":0.3240047086,"remaining_time":323.6807039},
{"learn":[14.22518863],"iteration":1,"passed_time":0.3250508542,"remaining_time":162.2003763},
{"learn":[13.8866124],"iteration":2,"passed_time":0.3311615016,"remaining_time":110.0560057},
{"learn":[13.52356875],"iteration":3,"passed_time":0.3471089894,"remaining_time":86.43013837},
{"learn":[13.18870211],"iteration":4,"passed_time":0.3480528174,"remaining_time":69.26251067},
{"learn":[12.9124226],"iteration":5,"passed_time":0.3489065275,"remaining_time":57.80218139},
{"learn":[12.60003351],"iteration":6,"passed_time":0.3503713533,"remaining_time":49.70267912},
{"learn":[12.32990573],"iteration":7,"passed_time":0.3513414207,"remaining_time":43.56633616},
{"learn":[12.0660619],"iteration":8,"passed_time":0.3521754512,"remaining_time":38.77843024},
{"learn":[11.77309809],"iteration":9,"passed_time":0.3573891195,"remaining_time":35.38152283},
{"learn":[11.49227636],"iteration":10,"passed_time":0.3776472168,"remaining_time":33.95391794},
{"learn":[11.26264833],"iteration":11,"passed_time":0.4696242303,"remaining_time":38.66572829},
{"learn":[11.04260393],"iteration":12,"passed_time":0.4704651506,"remaining_time":35.71916182},
{"learn":[10.79916926],"iteration":13,"passed_time":0.4719327964,"remaining_time":33.23755266},
{"learn":[10.5541002],"iteration":14,"passed_time":0.473020261,"remaining_time":31.06166381},
{"learn":[10.31918115],"iteration":15,"passed_time":0.4784421845,"remaining_time":29.42419435},
{"learn":[10.10004441],"iteration":16,"passed_time":0.479363733,"remaining_time":27.71850291},
{"learn":[9.894556723],"iteration":17,"passed_time":0.4802221129,"remaining_time":26.19878416},
{"learn":[9.690174082],"iteration":18,"passed_time":0.4812807482,"remaining_time":24.84928495},
{"learn":[9.506034866],"iteration":19,"passed_time":0.4823896324,"remaining_time":23.63709199},
{"learn":[9.338524633],"iteration":20,"passed_time":0.4839072269,"remaining_time":22.55929406},
{"learn":[9.170203312],"iteration":21,"passed_time":0.4850214509,"remaining_time":21.56140814},
{"learn":[9.010299969],"iteration":22,"passed_time":0.5580198574,"remaining_time":23.70371307},
{"learn":[8.843866678],"iteration":23,"passed_time":0.5591595008,"remaining_time":22.73915303},
{"learn":[8.690548059],"iteration":24,"passed_time":0.5647031714,"remaining_time":22.02342368},
{"learn":[8.555307687],"iteration":25,"passed_time":0.5657177777,"remaining_time":21.19265829},
{"learn":[8.413851302],"iteration":26,"passed_time":0.5668701708,"remaining_time":20.42832134},
{"learn":[8.29256019],"iteration":27,"passed_time":0.5761579041,"remaining_time":20.0009101},
{"learn":[8.162193833],"iteration":28,"passed_time":0.599858221,"remaining_time":20.08490802},
{"learn":[8.040736294],"iteration":29,"passed_time":0.6014483439,"remaining_time":19.44682978},
{"learn":[7.921220278],"iteration":30,"passed_time":0.6036074635,"remaining_time":18.86760104},
{"learn":[7.809589039],"iteration":31,"passed_time":0.6046232598,"remaining_time":18.28985361},
{"learn":[7.699675801],"iteration":32,"passed_time":0.605598767,"remaining_time":17.74587902},
{"learn":[7.60645267],"iteration":33,"passed_time":0.6066376228,"remaining_time":17.2356454},
{"learn":[7.498880302],"iteration":34,"passed_time":0.6075197922,"remaining_time":16.75018856},
{"learn":[7.401158744],"iteration":35,"passed_time":0.6084393007,"remaining_time":16.29265239},
{"learn":[7.306431077],"iteration":36,"passed_time":0.6573828385,"remaining_time":17.10972091},
{"learn":[7.223863468],"iteration":37,"passed_time":0.6596484956,"remaining_time":16.69952244},
{"learn":[7.143477682],"iteration":38,"passed_time":0.6605542045,"remaining_time":16.27673309},
{"learn":[7.062817131],"iteration":39,"passed_time":0.6618698538,"remaining_time":15.88487649},
{"learn":[6.990793435],"iteration":40,"passed_time":0.6629458887,"remaining_time":15.50646603},
{"learn":[6.931862224],"iteration":41,"passed_time":0.6772654145,"remaining_time":15.4481016},
{"learn":[6.858296558],"iteration":42,"passed_time":0.6783047603,"remaining_time":15.09622455},
{"learn":[6.786268161],"iteration":43,"passed_time":0.6889029929,"remaining_time":14.96798321},
{"learn":[6.717118549],"iteration":44,"passed_time":0.6897261037,"remaining_time":14.63752065},
{"learn":[6.652948106],"iteration":45,"passed_time":0.690785999,"remaining_time":14.32630094},
{"learn":[6.589686076],"iteration":46,"passed_time":0.6917055375,"remaining_time":14.02543356},
{"learn":[6.531283097],"iteration":47,"passed_time":0.6928263214,"remaining_time":13.74105537},
{"learn":[6.471368031],"iteration":48,"passed_time":0.7084331371,"remaining_time":13.74938599},
{"learn":[6.416481395],"iteration":49,"passed_time":0.7093154165,"remaining_time":13.47699291},
{"learn":[6.369870822],"iteration":50,"passed_time":0.710111478,"remaining_time":13.21364299},
{"learn":[6.325678067],"iteration":51,"passed_time":0.7108917298,"remaining_time":12.96010307},
{"learn":[6.275766122],"iteration":52,"passed_time":0.7120237533,"remaining_time":12.72238669},
{"learn":[6.224773967],"iteration":53,"passed_time":0.7200174668,"remaining_time":12.61363933},
{"learn":[6.182249254],"iteration":54,"passed_time":0.7210608224,"remaining_time":12.38913595},
{"learn":[6.139904173],"iteration":55,"passed_time":0.7220259399,"remaining_time":12.17129442},
{"learn":[6.100525536],"iteration":56,"passed_time":0.7232139322,"remaining_time":11.96474979},
{"learn":[6.062568564],"iteration":57,"passed_time":0.7242484981,"remaining_time":11.76279457},
{"learn":[6.030559288],"iteration":58,"passed_time":0.7251032881,"remaining_time":11.56478295},
{"learn":[5.997931376],"iteration":59,"passed_time":0.7259470384,"remaining_time":11.37317027},
{"learn":[5.964103835],"iteration":60,"passed_time":0.7353687985,"remaining_time":11.31985741},
{"learn":[5.933729724],"iteration":61,"passed_time":0.7362590378,"remaining_time":11.13888673},
{"learn":[5.901932711],"iteration":62,"passed_time":0.7370939183,"remaining_time":10.96280955},
{"learn":[5.873727795],"iteration":63,"passed_time":0.7379957772,"remaining_time":10.79318824},
{"learn":[5.846485734],"iteration":64,"passed_time":0.7389583748,"remaining_time":10.62963201},
{"learn":[5.820630862],"iteration":65,"passed_time":0.7508710668,"remaining_time":10.62596328},
{"learn":[5.793646238],"iteration":66,"passed_time":0.7518501639,"remaining_time":10.46979407},
{"learn":[5.765388646],"iteration":67,"passed_time":0.7527712324,"remaining_time":10.31739395},
{"learn":[5.747073912],"iteration":68,"passed_time":0.762000717,"remaining_time":10.28148794},
{"learn":[5.722315217],"iteration":69,"passed_time":0.7628194579,"remaining_time":10.13460137},
{"learn":[5.699970599],"iteration":70,"passed_time":0.7636111594,"remaining_time":9.991475593},
{"learn":[5.682732647],"iteration":71,"passed_time":0.7643921112,"remaining_time":9.852164989},
{"learn":[5.663525791],"iteration":72,"passed_time":0.7653113298,"remaining_time":9.718405516},
{"learn":[5.642381613],"iteration":73,"passed_time":0.7662925569,"remaining_time":9.589012266},
{"learn":[5.621404779],"iteration":74,"passed_time":0.7672063655,"remaining_time":9.462211842},
{"learn":[5.602460129],"iteration":75,"passed_time":0.768085985,"remaining_time":9.338308555},
{"learn":[5.587337574],"iteration":76,"passed_time":0.7769708377,"remaining_time":9.313559522},
{"learn":[5.572393026],"iteration":77,"passed_time":0.778070402,"remaining_time":9.197191162},
{"learn":[5.558425806],"iteration":78,"passed_time":0.7790532891,"remaining_time":9.08238075},
{"learn":[5.541518902],"iteration":79,"passed_time":0.7802731506,"remaining_time":8.973141232},
{"learn":[5.526157283],"iteration":80,"passed_time":0.7813029866,"remaining_time":8.864412897},
{"learn":[5.511746977],"iteration":81,"passed_time":0.7822555143,"remaining_time":8.75744588},
{"learn":[5.504975022],"iteration":82,"passed_time":0.7826381454,"remaining_time":8.6467371},
{"learn":[5.493980522],"iteration":83,"passed_time":0.7836640015,"remaining_time":8.545669349},
{"learn":[5.480745463],"iteration":84,"passed_time":0.7846039995,"remaining_time":8.446031289},
{"learn":[5.464052013],"iteration":85,"passed_time":0.7855593272,"remaining_time":8.348851454},
{"learn":[5.449143727],"iteration":86,"passed_time":0.7865371044,"remaining_time":8.254119268},
{"learn":[5.438255432],"iteration":87,"passed_time":0.7876569883,"remaining_time":8.162990606},
{"learn":[5.425927931],"iteration":88,"passed_time":0.7886347055,"remaining_time":8.072429401},
{"learn":[5.412331217],"iteration":89,"passed_time":0.7898180078,"remaining_time":7.985937635},
{"learn":[5.400691499],"iteration":90,"passed_time":0.7907858453,"remaining_time":7.899168498},
{"learn":[5.391618744],"iteration":91,"passed_time":0.7928405573,"remaining_time":7.824991587},
{"learn":[5.380766572],"iteration":92,"passed_time":0.8599785305,"remaining_time":8.387102443},
{"learn":[5.372207183],"iteration":93,"passed_time":0.8610769049,"remaining_time":8.2993157},
{"learn":[5.362918837],"iteration":94,"passed_time":0.8620867913,"remaining_time":8.212511012},
{"learn":[5.348292324],"iteration":95,"passed_time":0.8629258617,"remaining_time":8.125885198},
{"learn":[5.339772295],"iteration":96,"passed_time":0.8643078095,"remaining_time":8.046081979},
{"learn":[5.331515983],"iteration":97,"passed_time":0.8654091538,"remaining_time":7.965296497},
{"learn":[5.323861644],"iteration":98,"passed_time":0.8663146926,"remaining_time":7.884338768},
{"learn":[5.313277281],"iteration":99,"passed_time":0.8672262313,"remaining_time":7.805036082},
{"learn":[5.30685627],"iteration":100,"passed_time":0.8682482475,"remaining_time":7.728269054},
{"learn":[5.29652059],"iteration":101,"passed_time":0.8691073774,"remaining_time":7.651553186},
{"learn":[5.288350766],"iteration":102,"passed_time":0.8700212561,"remaining_time":7.576787056},
{"learn":[5.27993346],"iteration":103,"passed_time":0.8710371224,"remaining_time":7.504319824},
{"learn":[5.271789139],"iteration":104,"passed_time":0.872169376,"remaining_time":7.434205633},
{"learn":[5.262684686],"iteration":105,"passed_time":0.8734013072,"remaining_time":7.366233667},
{"learn":[5.251619772],"iteration":106,"passed_time":0.8746402183,"remaining_time":7.29956743},
{"learn":[5.241012171],"iteration":107,"passed_time":0.8755040982,"remaining_time":7.231015329},
{"learn":[5.232684032],"iteration":108,"passed_time":0.8763320288,"remaining_time":7.163411355},
{"learn":[5.224267141],"iteration":109,"passed_time":0.8773998239,"remaining_time":7.098962212},
{"learn":[5.216324968],"iteration":110,"passed_time":0.8783936807,"remaining_time":7.035062902},
{"learn":[5.211102527],"iteration":111,"passed_time":0.8835195511,"remaining_time":7.005047869},
{"learn":[5.206364257],"iteration":112,"passed_time":0.8847133132,"remaining_time":6.944608043},
{"learn":[5.196937641],"iteration":113,"passed_time":0.8858961256,"remaining_time":6.88512252},
{"learn":[5.190746047],"iteration":114,"passed_time":0.8869908301,"remaining_time":6.82597291},
{"learn":[5.181885213],"iteration":115,"passed_time":0.888152413,"remaining_time":6.768333906},
{"learn":[5.178293568],"iteration":116,"passed_time":0.8889302748,"remaining_time":6.708764382},
{"learn":[5.170991438],"iteration":117,"passed_time":0.8899620208,"remaining_time":6.652089003},
{"learn":[5.166257212],"iteration":118,"passed_time":0.8910682649,"remaining_time":6.596900348},
{"learn":[5.161421246],"iteration":119,"passed_time":0.8922907964,"remaining_time":6.54346584},
{"learn":[5.158223542],"iteration":120,"passed_time":0.8933821409,"remaining_time":6.489941338},
{"learn":[5.15470988],"iteration":121,"passed_time":0.8941289135,"remaining_time":6.434796607},
{"learn":[5.146388143],"iteration":122,"passed_time":0.8952390776,"remaining_time":6.383127407},
{"learn":[5.139529364],"iteration":123,"passed_time":0.8962554239,"remaining_time":6.331610898},
{"learn":[5.134276023],"iteration":124,"passed_time":0.8971696326,"remaining_time":6.280187428},
{"learn":[5.128536065],"iteration":125,"passed_time":0.902250884,"remaining_time":6.258470417},
{"learn":[5.123300353],"iteration":126,"passed_time":0.9030279758,"remaining_time":6.207428527},
{"learn":[5.116200518],"iteration":127,"passed_time":0.9039745437,"remaining_time":6.158326579},
{"learn":[5.108728704],"iteration":128,"passed_time":0.9212457307,"remaining_time":6.220194042},
{"learn":[5.104075866],"iteration":129,"passed_time":0.9223628146,"remaining_time":6.172735759},
{"learn":[5.100317606],"iteration":130,"passed_time":0.9233782209,"remaining_time":6.125310488},
{"learn":[5.095814182],"iteration":131,"passed_time":0.924533074,"remaining_time":6.079505365},
{"learn":[5.092146915],"iteration":132,"passed_time":0.9254010937,"remaining_time":6.032501867},
{"learn":[5.085258329],"iteration":133,"passed_time":0.9262161547,"remaining_time":5.985844701},
{"learn":[5.079219421],"iteration":134,"passed_time":0.9270196859,"remaining_time":5.939792802},
{"learn":[5.076476829],"iteration":135,"passed_time":0.9280425621,"remaining_time":5.895799806},
{"learn":[5.072133867],"iteration":136,"passed_time":0.929074868,"remaining_time":5.852493511},
{"learn":[5.067031564],"iteration":137,"passed_time":0.9298598897,"remaining_time":5.808255253},
{"learn":[5.061358312],"iteration":138,"passed_time":0.9309559741,"remaining_time":5.766569019},
{"learn":[5.056759124],"iteration":139,"passed_time":0.9319666405,"remaining_time":5.724937934},
{"learn":[5.050254],"iteration":140,"passed_time":0.933015576,"remaining_time":5.684116169},
{"learn":[5.048376474],"iteration":141,"passed_time":0.9460762112,"remaining_time":5.716432318},
{"learn":[5.042603751],"iteration":142,"passed_time":0.9470742779,"remaining_time":5.67582277},
{"learn":[5.037477349],"iteration":143,"passed_time":0.9480627848,"remaining_time":5.635706554},
{"learn":[5.03230489],"iteration":144,"passed_time":0.9490768112,"remaining_time":5.596280507},
{"learn":[5.025976187],"iteration":145,"passed_time":0.9500095394,"remaining_time":5.556905114},
{"learn":[5.01952451],"iteration":146,"passed_time":0.9509144383,"remaining_time":5.517891264},
{"learn":[5.017569424],"iteration":147,"passed_time":0.9519335445,"remaining_time":5.480049864},
{"learn":[5.008962367],"iteration":148,"passed_time":0.9530517984,"remaining_time":5.443268996},
{"learn":[5.003880266],"iteration":149,"passed_time":0.9540812244,"remaining_time":5.406460272},
{"learn":[4.996387564],"iteration":150,"passed_time":0.9551511594,"remaining_time":5.370353208},
{"learn":[4.993361683],"iteration":151,"passed_time":0.9562732432,"remaining_time":5.334998094},
{"learn":[4.99005752],"iteration":152,"passed_time":0.957225131,"remaining_time":5.299148274},
{"learn":[4.986908764],"iteration":153,"passed_time":0.9704076834,"remaining_time":5.33094091},
{"learn":[4.985207175],"iteration":154,"passed_time":0.9714314295,"remaining_time":5.295868116},
{"learn":[4.979003494],"iteration":155,"passed_time":0.9724272062,"remaining_time":5.261080526},
{"learn":[4.973142217],"iteration":156,"passed_time":0.9735242006,"remaining_time":5.227266886},
{"learn":[4.967056696],"iteration":157,"passed_time":0.9744647287,"remaining_time":5.193033554},
{"learn":[4.961460696],"iteration":158,"passed_time":0.9755613531,"remaining_time":5.160044641},
{"learn":[4.954240363],"iteration":159,"passed_time":0.9766772771,"remaining_time":5.127555705},
{"learn":[4.952320707],"iteration":160,"passed_time":0.9773439415,"remaining_time":5.093115323},
{"learn":[4.948337777],"iteration":161,"passed_time":0.9784899348,"remaining_time":5.061571391},
{"learn":[4.943228639],"iteration":162,"passed_time":0.9796183584,"remaining_time":5.030310221},
{"learn":[4.938545759],"iteration":163,"passed_time":0.9807208227,"remaining_time":4.999284194},
{"learn":[4.935330572],"iteration":164,"passed_time":0.9817099296,"remaining_time":4.96804722},
{"learn":[4.932051543],"iteration":165,"passed_time":0.9830382486,"remaining_time":4.938878912},
{"learn":[4.928964153],"iteration":166,"passed_time":0.9840603348,"remaining_time":4.90851652},
{"learn":[4.922860227],"iteration":167,"passed_time":0.9849784233,"remaining_time":4.877988382},
{"learn":[4.917668772],"iteration":168,"passed_time":0.9860526883,"remaining_time":4.848578603},
{"learn":[4.910365386],"iteration":169,"passed_time":0.9870636247,"remaining_time":4.819192991},
{"learn":[4.906457206],"iteration":170,"passed_time":0.9880870108,"remaining_time":4.790199602},
{"learn":[4.901996508],"iteration":171,"passed_time":0.989275923,"remaining_time":4.762328281},
{"learn":[4.896816173],"iteration":172,"passed_time":0.9904229563,"remaining_time":4.73456523},
{"learn":[4.891123132],"iteration":173,"passed_time":0.9914178631,"remaining_time":4.706385948},
{"learn":[4.887630202],"iteration":174,"passed_time":1.004928198,"remaining_time":4.737518647},
{"learn":[4.885259712],"iteration":175,"passed_time":1.005880546,"remaining_time":4.709349827},
{"learn":[4.880659728],"iteration":176,"passed_time":1.006787714,"remaining_time":4.681278469},
{"learn":[4.877299723],"iteration":177,"passed_time":1.007982276,"remaining_time":4.654839502},
{"learn":[4.874038772],"iteration":178,"passed_time":1.009325555,"remaining_time":4.629364697},
{"learn":[4.86943698],"iteration":179,"passed_time":1.010444559,"remaining_time":4.603136324},
{"learn":[4.861268711],"iteration":180,"passed_time":1.01127785,"remaining_time":4.57589259},
{"learn":[4.858673056],"iteration":181,"passed_time":1.012359924,"remaining_time":4.550057242},
{"learn":[4.854036207],"iteration":182,"passed_time":1.013284213,"remaining_time":4.523787988},
{"learn":[4.85130244],"iteration":183,"passed_time":1.08965907,"remaining_time":4.832401095},
{"learn":[4.847510084],"iteration":184,"passed_time":1.090636128,"remaining_time":4.804694292},
{"learn":[4.845691673],"iteration":185,"passed_time":1.091622245,"remaining_time":4.777314554},
{"learn":[4.842058646],"iteration":186,"passed_time":1.092523274,"remaining_time":4.749847173},
{"learn":[4.838623675],"iteration":187,"passed_time":1.101559533,"remaining_time":4.757799684},
{"learn":[4.834602161],"iteration":188,"passed_time":1.102490061,"remaining_time":4.730790685},
{"learn":[4.830858976],"iteration":189,"passed_time":1.141603498,"remaining_time":4.866835966},
{"learn":[4.827590511],"iteration":190,"passed_time":1.142509957,"remaining_time":4.839217567},
{"learn":[4.822246226],"iteration":191,"passed_time":1.143312868,"remaining_time":4.811441654},
{"learn":[4.816686395],"iteration":192,"passed_time":1.144285616,"remaining_time":4.784655398},
{"learn":[4.814797121],"iteration":193,"passed_time":1.145188074,"remaining_time":4.757843237},
{"learn":[4.811639392],"iteration":194,"passed_time":1.146106373,"remaining_time":4.731362207},
{"learn":[4.804813432],"iteration":195,"passed_time":1.159200637,"remaining_time":4.755088329},
{"learn":[4.80251613],"iteration":196,"passed_time":1.160134086,"remaining_time":4.728871425},
{"learn":[4.800087884],"iteration":197,"passed_time":1.160982036,"remaining_time":4.7025636},
{"learn":[4.794773135],"iteration":198,"passed_time":1.161824106,"remaining_time":4.676487985},
{"learn":[4.791664833],"iteration":199,"passed_time":1.162726325,"remaining_time":4.650905301},
{"learn":[4.785989873],"iteration":200,"passed_time":1.285709315,"remaining_time":5.110854442},
{"learn":[4.782387142],"iteration":201,"passed_time":1.286719752,"remaining_time":5.083180009},
{"learn":[4.778623704],"iteration":202,"passed_time":1.287582871,"remaining_time":5.055189894},
{"learn":[4.775772178],"iteration":203,"passed_time":1.288377253,"remaining_time":5.027197516},
{"learn":[4.77023101],"iteration":204,"passed_time":1.28935664,"remaining_time":5.000187945},
{"learn":[4.764496689],"iteration":205,"passed_time":1.357839642,"remaining_time":5.23361493},
{"learn":[4.763138716],"iteration":206,"passed_time":1.358676282,"remaining_time":5.204977255},
{"learn":[4.758053283],"iteration":207,"passed_time":1.359721138,"remaining_time":5.177399717},
{"learn":[4.755063788],"iteration":208,"passed_time":1.360753504,"remaining_time":5.150028811},
{"learn":[4.752465267],"iteration":209,"passed_time":1.361596434,"remaining_time":5.122196109},
{"learn":[4.748067377],"iteration":210,"passed_time":1.362448524,"remaining_time":5.094653486},
{"learn":[4.744163298],"iteration":211,"passed_time":1.363612777,"remaining_time":5.068522964},
{"learn":[4.736670896],"iteration":212,"passed_time":1.364510286,"remaining_time":5.041641292},
{"learn":[4.73349255],"iteration":213,"passed_time":1.365322827,"remaining_time":5.014690384},
{"learn":[4.731864595],"iteration":214,"passed_time":1.366315534,"remaining_time":4.988640438},
{"learn":[4.728398311],"iteration":215,"passed_time":1.367200283,"remaining_time":4.962430658},
{"learn":[4.723865975],"iteration":216,"passed_time":1.368009454,"remaining_time":4.93618158},
{"learn":[4.723483365],"iteration":217,"passed_time":1.406979675,"remaining_time":5.047055531},
{"learn":[4.72095416],"iteration":218,"passed_time":1.407847265,"remaining_time":5.020679058},
{"learn":[4.716173382],"iteration":219,"passed_time":1.408772193,"remaining_time":4.994737776},
{"learn":[4.710563974],"iteration":220,"passed_time":1.409595154,"remaining_time":4.968663461},
{"learn":[4.707160263],"iteration":221,"passed_time":1.410404515,"remaining_time":4.942768976},
{"learn":[4.70408351],"iteration":222,"passed_time":1.449774506,"remaining_time":5.051456464},
{"learn":[4.702501831],"iteration":223,"passed_time":1.450862081,"remaining_time":5.02620078},
{"learn":[4.700269738],"iteration":224,"passed_time":1.451800669,"remaining_time":5.000646749},
{"learn":[4.695346302],"iteration":225,"passed_time":1.452916873,"remaining_time":4.975918848},
{"learn":[4.689769299],"iteration":226,"passed_time":1.453947839,"remaining_time":4.95110872},
{"learn":[4.687919514],"iteration":227,"passed_time":1.455108532,"remaining_time":4.926946432},
{"learn":[4.682982074],"iteration":228,"passed_time":1.456091189,"remaining_time":4.902385618},
{"learn":[4.679578702],"iteration":229,"passed_time":1.457150154,"remaining_time":4.878285299},
{"learn":[4.675751423],"iteration":230,"passed_time":1.473684988,"remaining_time":4.905903706},
{"learn":[4.672710726],"iteration":231,"passed_time":1.474695705,"remaining_time":4.881751298},
{"learn":[4.6690533],"iteration":232,"passed_time":1.475878567,"remaining_time":4.85836421},
{"learn":[4.667595702],"iteration":233,"passed_time":1.519920439,"remaining_time":4.975466053},
{"learn":[4.664241291],"iteration":234,"passed_time":1.520892137,"remaining_time":4.950989296},
{"learn":[4.662246999],"iteration":235,"passed_time":1.521771476,"remaining_time":4.926412745},
{"learn":[4.658668443],"iteration":236,"passed_time":1.523168823,"remaining_time":4.903703849},
{"learn":[4.658017572],"iteration":237,"passed_time":1.523969175,"remaining_time":4.879262652},
{"learn":[4.657656705],"iteration":238,"passed_time":1.549071849,"remaining_time":4.932400322},
{"learn":[4.653242871],"iteration":239,"passed_time":1.549995777,"remaining_time":4.908319962},
{"learn":[4.6507302],"iteration":240,"passed_time":1.550826648,"remaining_time":4.884138696},
{"learn":[4.647671336],"iteration":241,"passed_time":1.552141137,"remaining_time":4.861665215},
{"learn":[4.645506007],"iteration":242,"passed_time":1.554201229,"remaining_time":4.841688603},
{"learn":[4.641297906],"iteration":243,"passed_time":1.555261795,"remaining_time":4.818761953},
{"learn":[4.63798107],"iteration":244,"passed_time":1.556249541,"remaining_time":4.795789403},
{"learn":[4.635062318],"iteration":245,"passed_time":1.557074792,"remaining_time":4.772497534},
{"learn":[4.631606017],"iteration":246,"passed_time":1.558659225,"remaining_time":4.75170201},
{"learn":[4.630215494],"iteration":247,"passed_time":1.559542035,"remaining_time":4.728933911},
{"learn":[4.62729814],"iteration":248,"passed_time":1.560650149,"remaining_time":4.707021131},
{"learn":[4.624691756],"iteration":249,"passed_time":1.561628496,"remaining_time":4.684885488},
{"learn":[4.621840053],"iteration":250,"passed_time":1.562779419,"remaining_time":4.663433406},
{"learn":[4.619602091],"iteration":251,"passed_time":1.572761806,"remaining_time":4.668356472},
{"learn":[4.613584029],"iteration":252,"passed_time":1.573603106,"remaining_time":4.646172018},
{"learn":[4.6119388],"iteration":253,"passed_time":1.574375168,"remaining_time":4.623952266},
{"learn":[4.60870702],"iteration":254,"passed_time":1.576656145,"remaining_time":4.60630913},
{"learn":[4.604771557],"iteration":255,"passed_time":1.586975904,"remaining_time":4.612148722},
{"learn":[4.604231277],"iteration":256,"passed_time":1.588050989,"remaining_time":4.591135739},
{"learn":[4.600750354],"iteration":257,"passed_time":1.588924879,"remaining_time":4.569698683},
{"learn":[4.596488253],"iteration":258,"passed_time":1.589704851,"remaining_time":4.548151716},
{"learn":[4.59470784],"iteration":259,"passed_time":1.610790899,"remaining_time":4.584558711},
{"learn":[4.588818005],"iteration":260,"passed_time":1.611829714,"remaining_time":4.563763061},
{"learn":[4.585054174],"iteration":261,"passed_time":1.612718804,"remaining_time":4.542696477},
{"learn":[4.581471435],"iteration":262,"passed_time":1.677697707,"remaining_time":4.701381027},
{"learn":[4.577555199],"iteration":263,"passed_time":1.678674524,"remaining_time":4.679941098},
{"learn":[4.57457145],"iteration":264,"passed_time":1.679506225,"remaining_time":4.658253115},
{"learn":[4.573029224],"iteration":265,"passed_time":1.680727876,"remaining_time":4.637797975},
{"learn":[4.571326203],"iteration":266,"passed_time":1.681565997,"remaining_time":4.616433992},
{"learn":[4.571019224],"iteration":267,"passed_time":1.68229202,"remaining_time":4.59491701},
{"learn":[4.565766631],"iteration":268,"passed_time":1.683027763,"remaining_time":4.573581021},
{"learn":[4.563383471],"iteration":269,"passed_time":1.683784715,"remaining_time":4.552454971},
{"learn":[4.558165805],"iteration":270,"passed_time":1.69686974,"remaining_time":4.564642215},
{"learn":[4.55629209],"iteration":271,"passed_time":1.697890896,"remaining_time":4.544355045},
{"learn":[4.549383848],"iteration":272,"passed_time":1.698770655,"remaining_time":4.523832478},
{"learn":[4.546227503],"iteration":273,"passed_time":1.699566997,"remaining_time":4.503232262},
{"learn":[4.540620977],"iteration":274,"passed_time":1.704666888,"remaining_time":4.494121795},
{"learn":[4.532898237],"iteration":275,"passed_time":1.705526058,"remaining_time":4.47391618},
{"learn":[4.529757367],"iteration":276,"passed_time":1.706339099,"remaining_time":4.45372985},
{"learn":[4.52579294],"iteration":277,"passed_time":1.707115451,"remaining_time":4.433587609},
{"learn":[4.521572155],"iteration":278,"passed_time":1.732066378,"remaining_time":4.476056842},
{"learn":[4.518818099],"iteration":279,"passed_time":1.733175722,"remaining_time":4.456737572},
{"learn":[4.514012334],"iteration":280,"passed_time":1.733983154,"remaining_time":4.4367754},
{"learn":[4.508331416],"iteration":281,"passed_time":1.734812834,"remaining_time":4.417005727},
{"learn":[4.506038537],"iteration":282,"passed_time":1.736208732,"remaining_time":4.398804455},
{"learn":[4.505805643],"iteration":283,"passed_time":1.737045712,"remaining_time":4.379312429},
{"learn":[4.501550352],"iteration":284,"passed_time":1.737849793,"remaining_time":4.35986878},
{"learn":[4.494692643],"iteration":285,"passed_time":1.738654465,"remaining_time":4.34055695},
{"learn":[4.489330245],"iteration":286,"passed_time":1.745475385,"remaining_time":4.336320383},
{"learn":[4.484826955],"iteration":287,"passed_time":1.746315476,"remaining_time":4.317279926},
{"learn":[4.478285428],"iteration":288,"passed_time":1.763662301,"remaining_time":4.338975419},
{"learn":[4.475311671],"iteration":289,"passed_time":1.764464952,"remaining_time":4.319896952},
{"learn":[4.471581298],"iteration":290,"passed_time":1.765240984,"remaining_time":4.300879236},
{"learn":[4.469164956],"iteration":291,"passed_time":1.765995217,"remaining_time":4.281933607},
{"learn":[4.462068024],"iteration":292,"passed_time":1.766976714,"remaining_time":4.263660534},
{"learn":[4.458540976],"iteration":293,"passed_time":1.767811474,"remaining_time":4.245152724},
{"learn":[4.455757458],"iteration":294,"passed_time":1.768614035,"remaining_time":4.22668778},
{"learn":[4.453027414],"iteration":295,"passed_time":1.769425017,"remaining_time":4.208362201},
{"learn":[4.450659338],"iteration":296,"passed_time":1.782638958,"remaining_time":4.219512416},
{"learn":[4.444696901],"iteration":297,"passed_time":1.783664914,"remaining_time":4.201787818},
{"learn":[4.442052813],"iteration":298,"passed_time":1.784664441,"remaining_time":4.184112953},
{"learn":[4.440036756],"iteration":299,"passed_time":1.785767495,"remaining_time":4.166790822},
{"learn":[4.435017051],"iteration":300,"passed_time":1.786780282,"remaining_time":4.149366833},
{"learn":[4.429962125],"iteration":301,"passed_time":1.78771582,"remaining_time":4.131872987},
{"learn":[4.427666256],"iteration":302,"passed_time":1.788649828,"remaining_time":4.114484918},
{"learn":[4.425030004],"iteration":303,"passed_time":1.790010136,"remaining_time":4.098181101},
{"learn":[4.422588771],"iteration":304,"passed_time":1.790915905,"remaining_time":4.080939521},
{"learn":[4.418936667],"iteration":305,"passed_time":1.795758452,"remaining_time":4.072733221},
{"learn":[4.416887976],"iteration":306,"passed_time":1.796658711,"remaining_time":4.055649794},
{"learn":[4.413773354],"iteration":307,"passed_time":1.797713826,"remaining_time":4.039019376},
{"learn":[4.411129391],"iteration":308,"passed_time":1.799162413,"remaining_time":4.023369667},
{"learn":[4.40850819],"iteration":309,"passed_time":1.800263777,"remaining_time":4.007038729},
{"learn":[4.404880292],"iteration":310,"passed_time":1.802214261,"remaining_time":3.9926869},
{"learn":[4.404593827],"iteration":311,"passed_time":1.803082071,"remaining_time":3.976027131},
{"learn":[4.402139942],"iteration":312,"passed_time":1.803908562,"remaining_time":3.959377578},
{"learn":[4.400284725],"iteration":313,"passed_time":1.80485905,"remaining_time":3.943099707},
{"learn":[4.395805521],"iteration":314,"passed_time":1.805779578,"remaining_time":3.926854003},
{"learn":[4.392838833],"iteration":315,"passed_time":1.862469075,"remaining_time":4.031420403},
{"learn":[4.389213061],"iteration":316,"passed_time":1.863457352,"remaining_time":4.014957008},
{"learn":[4.3861981],"iteration":317,"passed_time":1.865298499,"remaining_time":4.000420052},
{"learn":[4.385054234],"iteration":318,"passed_time":1.866607469,"remaining_time":3.984826602},
{"learn":[4.379364607],"iteration":319,"passed_time":1.871953384,"remaining_time":3.977900941},
{"learn":[4.378387619],"iteration":320,"passed_time":1.872951491,"remaining_time":3.961788355},
{"learn":[4.375816727],"iteration":321,"passed_time":1.873891209,"remaining_time":3.945646706},
{"learn":[4.374600202],"iteration":322,"passed_time":1.875015982,"remaining_time":3.929987059},
{"learn":[4.37098897],"iteration":323,"passed_time":1.876042128,"remaining_time":3.914211354},
{"learn":[4.367418484],"iteration":324,"passed_time":1.877199521,"remaining_time":3.898799006},
{"learn":[4.363584638],"iteration":325,"passed_time":1.878211338,"remaining_time":3.883173134},
{"learn":[4.360770706],"iteration":326,"passed_time":1.879246734,"remaining_time":3.867685173},
{"learn":[4.358675808],"iteration":327,"passed_time":1.880128393,"remaining_time":3.851970366},
{"learn":[4.354228195],"iteration":328,"passed_time":1.881203178,"remaining_time":3.836739612},
{"learn":[4.353773425],"iteration":329,"passed_time":1.882243204,"remaining_time":3.82152408},
{"learn":[4.351648009],"iteration":330,"passed_time":1.95353091,"remaining_time":3.948375163},
{"learn":[4.348209927],"iteration":331,"passed_time":1.954364951,"remaining_time":3.932276467},
{"learn":[4.345852733],"iteration":332,"passed_time":1.955129393,"remaining_time":3.916130045},
{"learn":[4.34237339],"iteration":333,"passed_time":1.955952673,"remaining_time":3.900193056},
{"learn":[4.340814362],"iteration":334,"passed_time":1.956759385,"remaining_time":3.884313405},
{"learn":[4.339707068],"iteration":335,"passed_time":1.957561436,"remaining_time":3.868514266},
{"learn":[4.335430786],"iteration":336,"passed_time":1.958619781,"remaining_time":3.853308353},
{"learn":[4.33521887],"iteration":337,"passed_time":1.959444452,"remaining_time":3.837728483},
{"learn":[4.328507238],"iteration":338,"passed_time":1.960269293,"remaining_time":3.822235996},
{"learn":[4.326140732],"iteration":339,"passed_time":1.961206371,"remaining_time":3.807047661},
{"learn":[4.323785636],"iteration":340,"passed_time":1.962187088,"remaining_time":3.792027246},
{"learn":[4.320632534],"iteration":341,"passed_time":1.963153575,"remaining_time":3.777061557},
{"learn":[4.31973724],"iteration":342,"passed_time":1.964067654,"remaining_time":3.76207711},
{"learn":[4.318000924],"iteration":343,"passed_time":1.965012662,"remaining_time":3.747233449},
{"learn":[4.312713628],"iteration":344,"passed_time":1.96639194,"remaining_time":3.733294842},
{"learn":[4.308220789],"iteration":345,"passed_time":1.967183981,"remaining_time":3.718318855},
{"learn":[4.305890947],"iteration":346,"passed_time":1.968390283,"remaining_time":3.704204193},
{"learn":[4.305137856],"iteration":347,"passed_time":1.969136696,"remaining_time":3.689302085},
{"learn":[4.304787172],"iteration":348,"passed_time":1.969867549,"remaining_time":3.674452075},
{"learn":[4.30350134],"iteration":349,"passed_time":1.970860836,"remaining_time":3.660170123},
{"learn":[4.30293809],"iteration":350,"passed_time":1.971670907,"remaining_time":3.645625124},
{"learn":[4.299548459],"iteration":351,"passed_time":1.972486918,"remaining_time":3.631169098},
{"learn":[4.294768408],"iteration":352,"passed_time":1.973284559,"remaining_time":3.616756685},
{"learn":[4.294581479],"iteration":353,"passed_time":1.974230287,"remaining_time":3.602691428},
{"learn":[4.292551604],"iteration":354,"passed_time":1.975033418,"remaining_time":3.588440999},
{"learn":[4.288628894],"iteration":355,"passed_time":1.97582093,"remaining_time":3.574237862},
{"learn":[4.287802767],"iteration":356,"passed_time":1.976618191,"remaining_time":3.560127442},
{"learn":[4.284566905],"iteration":357,"passed_time":1.988969803,"remaining_time":3.56681177},
{"learn":[4.27890232],"iteration":358,"passed_time":1.989884232,"remaining_time":3.552968781},
{"learn":[4.276938023],"iteration":359,"passed_time":1.990725512,"remaining_time":3.539067577},
{"learn":[4.273425094],"iteration":360,"passed_time":1.991585272,"remaining_time":3.525271437},
{"learn":[4.269726505],"iteration":361,"passed_time":1.992570239,"remaining_time":3.511767438},
{"learn":[4.265565857],"iteration":362,"passed_time":1.993455418,"remaining_time":3.498157304},
{"learn":[4.262117173],"iteration":363,"passed_time":1.994290029,"remaining_time":3.484528732},
{"learn":[4.259185148],"iteration":364,"passed_time":1.995166928,"remaining_time":3.471043834},
{"learn":[4.257668507],"iteration":365,"passed_time":1.996108456,"remaining_time":3.457739785},
{"learn":[4.253432436],"iteration":366,"passed_time":1.99681017,"remaining_time":3.444089476},
{"learn":[4.250216667],"iteration":367,"passed_time":2.003712819,"remaining_time":3.441158972},
{"learn":[4.24514828],"iteration":368,"passed_time":2.004570549,"remaining_time":3.427869963},
{"learn":[4.244015772],"iteration":369,"passed_time":2.006329218,"remaining_time":3.416182182},
{"learn":[4.240329192],"iteration":370,"passed_time":2.007143239,"remaining_time":3.402946354},
{"learn":[4.236718014],"iteration":371,"passed_time":2.00839534,"remaining_time":3.390516864},
{"learn":[4.233495944],"iteration":372,"passed_time":2.009342278,"remaining_time":3.377634338},
{"learn":[4.230357491],"iteration":373,"passed_time":2.010215857,"remaining_time":3.364692852},
{"learn":[4.227381215],"iteration":374,"passed_time":2.011015938,"remaining_time":3.351693231},
{"learn":[4.226169067],"iteration":375,"passed_time":2.01179175,"remaining_time":3.338718224},
{"learn":[4.225963861],"iteration":376,"passed_time":2.039303108,"remaining_time":3.369988956},
{"learn":[4.224346548],"iteration":377,"passed_time":2.040277866,"remaining_time":3.357282625},
{"learn":[4.222595381],"iteration":378,"passed_time":2.041189834,"remaining_time":3.344535322},
{"learn":[4.219700938],"iteration":379,"passed_time":2.042018125,"remaining_time":3.331713783},
{"learn":[4.216356207],"iteration":380,"passed_time":2.043122429,"remaining_time":3.319403632},
{"learn":[4.214326494],"iteration":381,"passed_time":2.04394434,"remaining_time":3.306695294},
{"learn":[4.212901398],"iteration":382,"passed_time":2.044745801,"remaining_time":3.294016082},
{"learn":[4.211331091],"iteration":383,"passed_time":2.065477977,"remaining_time":3.313370922},
{"learn":[4.208624791],"iteration":384,"passed_time":2.066425585,"remaining_time":3.300913597},
{"learn":[4.204659106],"iteration":385,"passed_time":2.067260286,"remaining_time":3.28833631},
{"learn":[4.202968852],"iteration":386,"passed_time":2.068091266,"remaining_time":3.275813815},
{"learn":[4.197261935],"iteration":387,"passed_time":2.069096953,"remaining_time":3.263627153},
{"learn":[4.196934403],"iteration":388,"passed_time":2.127427872,"remaining_time":3.34153838},
{"learn":[4.192479929],"iteration":389,"passed_time":2.128306641,"remaining_time":3.328889875},
{"learn":[4.190243116],"iteration":390,"passed_time":2.129075673,"remaining_time":3.316130652},
{"learn":[4.185852431],"iteration":391,"passed_time":2.134075817,"remaining_time":3.309995144},
{"learn":[4.180967944],"iteration":392,"passed_time":2.135069803,"remaining_time":3.297677788},
{"learn":[4.178283162],"iteration":393,"passed_time":2.135991532,"remaining_time":3.285306772},
{"learn":[4.176341157],"iteration":394,"passed_time":2.137068047,"remaining_time":3.273230806},
{"learn":[4.176041504],"iteration":395,"passed_time":2.137965446,"remaining_time":3.260937195},
{"learn":[4.175564513],"iteration":396,"passed_time":2.138814766,"remaining_time":3.24862797},
{"learn":[4.170830274],"iteration":397,"passed_time":2.141942523,"remaining_time":3.23982261},
{"learn":[4.167804808],"iteration":398,"passed_time":2.155606494,"remaining_time":3.246916048},
{"learn":[4.165860548],"iteration":399,"passed_time":2.156437555,"remaining_time":3.234656332},
{"learn":[4.160950571],"iteration":400,"passed_time":2.157246016,"remaining_time":3.222419859},
{"learn":[4.158544115],"iteration":401,"passed_time":2.158004678,"remaining_time":3.210166163},
{"learn":[4.154448767],"iteration":402,"passed_time":2.158953636,"remaining_time":3.198251416},
{"learn":[4.15197457],"iteration":403,"passed_time":2.159784667,"remaining_time":3.186216983},
{"learn":[4.149562679],"iteration":404,"passed_time":2.160606677,"remaining_time":3.174224625},
{"learn":[4.149327961],"iteration":405,"passed_time":2.161469547,"remaining_time":3.162347072},
{"learn":[4.147444889],"iteration":406,"passed_time":2.162351457,"remaining_time":3.150551385},
{"learn":[4.147254809],"iteration":407,"passed_time":2.163129039,"remaining_time":3.138657821},
{"learn":[4.144589165],"iteration":408,"passed_time":2.163949729,"remaining_time":3.126880905},
{"learn":[4.141691034],"iteration":409,"passed_time":2.169109879,"remaining_time":3.121402021},
{"learn":[4.138893468],"iteration":410,"passed_time":2.169971469,"remaining_time":3.109764465},
{"learn":[4.136964597],"iteration":411,"passed_time":2.170806119,"remaining_time":3.098140772},
{"learn":[4.133773523],"iteration":412,"passed_time":2.171714658,"remaining_time":3.086674345},
{"learn":[4.131363444],"iteration":413,"passed_time":2.172561798,"remaining_time":3.075172014},
{"learn":[4.130228592],"iteration":414,"passed_time":2.1733473,"remaining_time":3.063634146},
{"learn":[4.12884186],"iteration":415,"passed_time":2.174118332,"remaining_time":3.052127659},
{"learn":[4.12413494],"iteration":416,"passed_time":2.21875314,"remaining_time":3.101997796},
{"learn":[4.119422508],"iteration":417,"passed_time":2.219699518,"remaining_time":3.090586411},
{"learn":[4.117038244],"iteration":418,"passed_time":2.220563688,"remaining_time":3.079110985},
{"learn":[4.116067631],"iteration":419,"passed_time":2.221558015,"remaining_time":3.06786583},
{"learn":[4.110343455],"iteration":420,"passed_time":2.222591841,"remaining_time":3.056723696},
{"learn":[4.105604544],"iteration":421,"passed_time":2.223749614,"remaining_time":3.045799234},
{"learn":[4.103390131],"iteration":422,"passed_time":2.22475853,"remaining_time":3.034717901},
{"learn":[4.096724402],"iteration":423,"passed_time":2.225731098,"remaining_time":3.023634699},
{"learn":[4.093431279],"iteration":424,"passed_time":2.226631067,"remaining_time":3.012500855},
{"learn":[4.091412744],"iteration":425,"passed_time":2.25435669,"remaining_time":3.037560422},
{"learn":[4.091192901],"iteration":426,"passed_time":2.255233339,"remaining_time":3.026343567},
{"learn":[4.088994581],"iteration":427,"passed_time":2.25603349,"remaining_time":3.015072796},
{"learn":[4.087845355],"iteration":428,"passed_time":2.321080932,"remaining_time":3.089364131},
{"learn":[4.083650279],"iteration":429,"passed_time":2.322112058,"remaining_time":3.078148542},
{"learn":[4.079840652],"iteration":430,"passed_time":2.323058036,"remaining_time":3.066867802},
{"learn":[4.075707828],"iteration":431,"passed_time":2.324214709,"remaining_time":3.055911933},
{"learn":[4.071345409],"iteration":432,"passed_time":2.325929549,"remaining_time":3.045732227},
{"learn":[4.067460475],"iteration":433,"passed_time":2.327157881,"remaining_time":3.034957052},
{"learn":[4.064914749],"iteration":434,"passed_time":2.328150087,"remaining_time":3.023919079},
{"learn":[4.063823175],"iteration":435,"passed_time":2.329224102,"remaining_time":3.013033013},
{"learn":[4.058898471],"iteration":436,"passed_time":2.330105632,"remaining_time":3.001943869},
{"learn":[4.054120355],"iteration":437,"passed_time":2.33362672,"remaining_time":2.994288165},
{"learn":[4.052715901],"iteration":438,"passed_time":2.334766713,"remaining_time":2.983608487},
{"learn":[4.052114167],"iteration":439,"passed_time":2.335705021,"remaining_time":2.972715481},
{"learn":[4.051377267],"iteration":440,"passed_time":2.337279994,"remaining_time":2.962674641},
{"learn":[4.049275336],"iteration":441,"passed_time":2.338188503,"remaining_time":2.951830735},
{"learn":[4.047099198],"iteration":442,"passed_time":2.339096302,"remaining_time":2.941030791},
{"learn":[4.044348685],"iteration":443,"passed_time":2.340184827,"remaining_time":2.93050172},
{"learn":[4.042822379],"iteration":444,"passed_time":2.341491136,"remaining_time":2.920286698},
{"learn":[4.041258611],"iteration":445,"passed_time":2.395354109,"remaining_time":2.975395014},
{"learn":[4.040044254],"iteration":446,"passed_time":2.396493692,"remaining_time":2.964789736},
{"learn":[4.036860137],"iteration":447,"passed_time":2.403559338,"remaining_time":2.96152847},
{"learn":[4.036372284],"iteration":448,"passed_time":2.404564404,"remaining_time":2.950812888},
{"learn":[4.03368231],"iteration":449,"passed_time":2.405843304,"remaining_time":2.94047515},
{"learn":[4.032439519],"iteration":450,"passed_time":2.406785772,"remaining_time":2.929768047},
{"learn":[4.032008634],"iteration":451,"passed_time":2.407695181,"remaining_time":2.919064069},
{"learn":[4.030034932],"iteration":452,"passed_time":2.413214082,"remaining_time":2.913969322},
{"learn":[4.028173412],"iteration":453,"passed_time":2.414040443,"remaining_time":2.903229255},
{"learn":[4.023806097],"iteration":454,"passed_time":2.414851014,"remaining_time":2.892513852},
{"learn":[4.020239186],"iteration":455,"passed_time":2.415656085,"remaining_time":2.88183533},
{"learn":[4.017384838],"iteration":456,"passed_time":2.416715191,"remaining_time":2.871501857},
{"learn":[4.016468229],"iteration":457,"passed_time":2.417740997,"remaining_time":2.861169476},
{"learn":[4.014530169],"iteration":458,"passed_time":2.424727934,"remaining_time":2.85790373},
{"learn":[4.012884822],"iteration":459,"passed_time":2.425554314,"remaining_time":2.847389847},
{"learn":[4.008924707],"iteration":460,"passed_time":2.426338026,"remaining_time":2.836868104},
{"learn":[4.008286778],"iteration":461,"passed_time":2.427137107,"remaining_time":2.826406415},
{"learn":[4.006444202],"iteration":462,"passed_time":2.476584513,"remaining_time":2.872410116},
{"learn":[4.003284363],"iteration":463,"passed_time":2.477491582,"remaining_time":2.861929931},
{"learn":[3.999811484],"iteration":464,"passed_time":2.478349262,"remaining_time":2.851434097},
{"learn":[3.997483319],"iteration":465,"passed_time":2.479380038,"remaining_time":2.841177984},
{"learn":[3.99708333],"iteration":466,"passed_time":2.480263098,"remaining_time":2.830792786},
{"learn":[3.995860263],"iteration":467,"passed_time":2.481091078,"remaining_time":2.820385585},
{"learn":[3.994131111],"iteration":468,"passed_time":2.48185605,"remaining_time":2.809947895},
{"learn":[3.993125499],"iteration":469,"passed_time":2.482614303,"remaining_time":2.799543788},
{"learn":[3.992954084],"iteration":470,"passed_time":2.563922035,"remaining_time":2.879649165},
{"learn":[3.990635743],"iteration":471,"passed_time":2.564925902,"remaining_time":2.869239144},
{"learn":[3.986678254],"iteration":472,"passed_time":2.565883419,"remaining_time":2.858817256},
{"learn":[3.986393291],"iteration":473,"passed_time":2.566831187,"remaining_time":2.848424482},
{"learn":[3.986152671],"iteration":474,"passed_time":2.567621699,"remaining_time":2.837897667},
{"learn":[3.985596662],"iteration":475,"passed_time":2.568397391,"remaining_time":2.827395447},
{"learn":[3.983853457],"iteration":476,"passed_time":2.622357831,"remaining_time":2.875247685},
{"learn":[3.983263928],"iteration":477,"passed_time":2.623244821,"remaining_time":2.864715055},
{"learn":[3.980067202],"iteration":478,"passed_time":2.628504098,"remaining_time":2.858978361},
{"learn":[3.978115407],"iteration":479,"passed_time":2.629367428,"remaining_time":2.84848138},
{"learn":[3.972661644],"iteration":480,"passed_time":2.668308119,"remaining_time":2.879110008},
{"learn":[3.969938254],"iteration":481,"passed_time":2.669318066,"remaining_time":2.86868622},
{"learn":[3.968211434],"iteration":482,"passed_time":2.670555457,"remaining_time":2.858544868},
{"learn":[3.966113368],"iteration":483,"passed_time":2.671434816,"remaining_time":2.848058606},
{"learn":[3.962246044],"iteration":484,"passed_time":2.672609959,"remaining_time":2.837926039},
{"learn":[3.961319703],"iteration":485,"passed_time":2.673467359,"remaining_time":2.827494285},
{"learn":[3.96078191],"iteration":486,"passed_time":2.67427384,"remaining_time":2.817048213},
{"learn":[3.958913633],"iteration":487,"passed_time":2.675276636,"remaining_time":2.806847619},
{"learn":[3.957428286],"iteration":488,"passed_time":2.737745819,"remaining_time":2.860916387},
{"learn":[3.952641965],"iteration":489,"passed_time":2.751077008,"remaining_time":2.863365865},
{"learn":[3.951486786],"iteration":490,"passed_time":2.752042675,"remaining_time":2.852932223},
{"learn":[3.94938344],"iteration":491,"passed_time":2.753213378,"remaining_time":2.842748772},
{"learn":[3.947297924],"iteration":492,"passed_time":2.813769354,"remaining_time":2.893673555},
{"learn":[3.946284886],"iteration":493,"passed_time":2.814654844,"remaining_time":2.883027026},
{"learn":[3.943288204],"iteration":494,"passed_time":2.81567413,"remaining_time":2.872556436},
{"learn":[3.943076488],"iteration":495,"passed_time":2.816571899,"remaining_time":2.862000478},
{"learn":[3.942347078],"iteration":496,"passed_time":2.827397546,"remaining_time":2.861531118},
{"learn":[3.940251541],"iteration":497,"passed_time":2.855011452,"remaining_time":2.877943271},
{"learn":[3.939011019],"iteration":498,"passed_time":2.855894931,"remaining_time":2.867341404},
{"learn":[3.938760512],"iteration":499,"passed_time":2.856700373,"remaining_time":2.856700373},
{"learn":[3.934522727],"iteration":500,"passed_time":2.85768041,"remaining_time":2.846272504},
{"learn":[3.930091193],"iteration":501,"passed_time":2.858637137,"remaining_time":2.835859152},
{"learn":[3.927671752],"iteration":502,"passed_time":2.859448978,"remaining_time":2.825340243},
{"learn":[3.927280041],"iteration":503,"passed_time":2.87353527,"remaining_time":2.827923599},
{"learn":[3.925987561],"iteration":504,"passed_time":2.896511823,"remaining_time":2.839155154},
{"learn":[3.921645957],"iteration":505,"passed_time":2.897667586,"remaining_time":2.828948197},
{"learn":[3.920333743],"iteration":506,"passed_time":2.898630004,"remaining_time":2.818588939},
{"learn":[3.918659461],"iteration":507,"passed_time":2.900565849,"remaining_time":2.809209444},
{"learn":[3.916124385],"iteration":508,"passed_time":2.902492054,"remaining_time":2.799849899},
{"learn":[3.913849268],"iteration":509,"passed_time":2.903339214,"remaining_time":2.789482774},
{"learn":[3.912826119],"iteration":510,"passed_time":2.904124846,"remaining_time":2.779094031},
{"learn":[3.910034145],"iteration":511,"passed_time":2.906874342,"remaining_time":2.770614607},
{"learn":[3.90792379],"iteration":512,"passed_time":2.907858709,"remaining_time":2.760481854},
{"learn":[3.907823851],"iteration":513,"passed_time":2.916398839,"remaining_time":2.757528864},
{"learn":[3.904527401],"iteration":514,"passed_time":2.917596331,"remaining_time":2.747639264},
{"learn":[3.903378283],"iteration":515,"passed_time":2.918602478,"remaining_time":2.737603875},
{"learn":[3.902170135],"iteration":516,"passed_time":2.91978045,"remaining_time":2.727763941},
{"learn":[3.899435429],"iteration":517,"passed_time":2.971886114,"remaining_time":2.765345767},
{"learn":[3.897497505],"iteration":518,"passed_time":2.973027768,"remaining_time":2.755349434},
{"learn":[3.896426119],"iteration":519,"passed_time":2.973936757,"remaining_time":2.745172391},
{"learn":[3.896044669],"iteration":520,"passed_time":2.974739328,"remaining_time":2.734933086},
{"learn":[3.892795942],"iteration":521,"passed_time":2.975650777,"remaining_time":2.724829638},
{"learn":[3.892413888],"iteration":522,"passed_time":2.980344897,"remaining_time":2.718211311},
{"learn":[3.891738985],"iteration":523,"passed_time":2.981196857,"remaining_time":2.708110122},
{"learn":[3.88822057],"iteration":524,"passed_time":2.982058787,"remaining_time":2.698053188},
{"learn":[3.883837053],"iteration":525,"passed_time":2.982860028,"remaining_time":2.687976527},
{"learn":[3.881769742],"iteration":526,"passed_time":2.98363551,"remaining_time":2.677911948},
{"learn":[3.880356898],"iteration":527,"passed_time":2.98451338,"remaining_time":2.667974082},
{"learn":[3.879250273],"iteration":528,"passed_time":2.985639333,"remaining_time":2.658291354},
{"learn":[3.877174493],"iteration":529,"passed_time":2.986462014,"remaining_time":2.648371975},
{"learn":[3.875854201],"iteration":530,"passed_time":2.987277485,"remaining_time":2.638480491},
{"learn":[3.873189396],"iteration":531,"passed_time":3.015210193,"remaining_time":2.65247814},
{"learn":[3.871583368],"iteration":532,"passed_time":3.016332537,"remaining_time":2.642827945},
{"learn":[3.869622679],"iteration":533,"passed_time":3.017156748,"remaining_time":2.632949522},
{"learn":[3.866860164],"iteration":534,"passed_time":3.01792745,"remaining_time":2.623058438},
{"learn":[3.864498444],"iteration":535,"passed_time":3.018692262,"remaining_time":2.613196287},
{"learn":[3.861416322],"iteration":536,"passed_time":3.024111086,"remaining_time":2.607380694},
{"learn":[3.860265769],"iteration":537,"passed_time":3.025038734,"remaining_time":2.597709842},
{"learn":[3.859328725],"iteration":538,"passed_time":3.025924773,"remaining_time":2.588035845},
{"learn":[3.858521278],"iteration":539,"passed_time":3.02694504,"remaining_time":2.578508737},
{"learn":[3.85599111],"iteration":540,"passed_time":3.028024614,"remaining_time":2.569063397},
{"learn":[3.852379816],"iteration":541,"passed_time":3.029009141,"remaining_time":2.55956861},
{"learn":[3.851327537],"iteration":542,"passed_time":3.030091426,"remaining_time":2.550187443},
{"learn":[3.847854898],"iteration":543,"passed_time":3.031337457,"remaining_time":2.540974045},
{"learn":[3.847083414],"iteration":544,"passed_time":3.032405952,"remaining_time":2.531641666},
{"learn":[3.845397429],"iteration":545,"passed_time":3.033373819,"remaining_time":2.522255887},
{"learn":[3.841933528],"iteration":546,"passed_time":3.0384866,"remaining_time":2.51633351},
{"learn":[3.840996474],"iteration":547,"passed_time":3.039490577,"remaining_time":2.507025074},
{"learn":[3.838355966],"iteration":548,"passed_time":3.040431415,"remaining_time":2.497695024},
{"learn":[3.83342799],"iteration":549,"passed_time":3.042072916,"remaining_time":2.48896875},
{"learn":[3.828161535],"iteration":550,"passed_time":3.042938336,"remaining_time":2.479635777},
{"learn":[3.823502399],"iteration":551,"passed_time":3.043782167,"remaining_time":2.470315961},
{"learn":[3.820068862],"iteration":552,"passed_time":3.044818302,"remaining_time":2.461182244},
{"learn":[3.817951642],"iteration":553,"passed_time":3.046240179,"remaining_time":2.452388303},
{"learn":[3.815785958],"iteration":554,"passed_time":3.04750004,"remaining_time":2.443491023},
{"learn":[3.81503012],"iteration":555,"passed_time":3.065378103,"remaining_time":2.447891866},
{"learn":[3.813529315],"iteration":556,"passed_time":3.066384709,"remaining_time":2.438794302},
{"learn":[3.808881326],"iteration":557,"passed_time":3.067296368,"remaining_time":2.429650528},
{"learn":[3.808740434],"iteration":558,"passed_time":3.068150118,"remaining_time":2.420490522},
{"learn":[3.80714352],"iteration":559,"passed_time":3.074233816,"remaining_time":2.415469427},
{"learn":[3.80573346],"iteration":560,"passed_time":3.075429468,"remaining_time":2.406619495},
{"learn":[3.803370052],"iteration":561,"passed_time":3.076699008,"remaining_time":2.397854387},
{"learn":[3.803215211],"iteration":562,"passed_time":3.077692635,"remaining_time":2.388901743},
{"learn":[3.801309667],"iteration":563,"passed_time":3.087672722,"remaining_time":2.386924303},
{"learn":[3.800003847],"iteration":564,"passed_time":3.088713958,"remaining_time":2.37803641},
{"learn":[3.798026138],"iteration":565,"passed_time":3.111834638,"remaining_time":2.386106419},
{"learn":[3.794745847],"iteration":566,"passed_time":3.113324384,"remaining_time":2.377547545},
{"learn":[3.794312041],"iteration":567,"passed_time":3.114402648,"remaining_time":2.368700606},
{"learn":[3.792205926],"iteration":568,"passed_time":3.11521594,"remaining_time":2.359680263},
{"learn":[3.788991061],"iteration":569,"passed_time":3.116028981,"remaining_time":2.350688529},
{"learn":[3.787391572],"iteration":570,"passed_time":3.117495036,"remaining_time":2.342216061},
{"learn":[3.7826445],"iteration":571,"passed_time":3.130826635,"remaining_time":2.342646503},
{"learn":[3.781700331],"iteration":572,"passed_time":3.131933139,"remaining_time":2.333918762},
{"learn":[3.780045374],"iteration":573,"passed_time":3.132991705,"remaining_time":2.325181997},
{"learn":[3.775462644],"iteration":574,"passed_time":3.150579944,"remaining_time":2.328689524},
{"learn":[3.773711943],"iteration":575,"passed_time":3.152595767,"remaining_time":2.320660773},
{"learn":[3.772415806],"iteration":576,"passed_time":3.195941856,"remaining_time":2.342952175},
{"learn":[3.770170875],"iteration":577,"passed_time":3.197796982,"remaining_time":2.334723748},
{"learn":[3.765166479],"iteration":578,"passed_time":3.201140504,"remaining_time":2.327599572},
{"learn":[3.763976102],"iteration":579,"passed_time":3.205023864,"remaining_time":2.32087935},
{"learn":[3.760761708],"iteration":580,"passed_time":3.206005781,"remaining_time":2.312076458},
{"learn":[3.758155662],"iteration":581,"passed_time":3.208301837,"remaining_time":2.304244275},
{"learn":[3.756844548],"iteration":582,"passed_time":3.209186127,"remaining_time":2.295421295},
{"learn":[3.753098923],"iteration":583,"passed_time":3.209989948,"remaining_time":2.286568182},
{"learn":[3.751618946],"iteration":584,"passed_time":3.212367902,"remaining_time":2.278859281},
{"learn":[3.751398464],"iteration":585,"passed_time":3.213186423,"remaining_time":2.270066859},
{"learn":[3.749920103],"iteration":586,"passed_time":3.213959995,"remaining_time":2.26126998},
{"learn":[3.748237465],"iteration":587,"passed_time":3.215437851,"remaining_time":2.252993868},
{"learn":[3.746021536],"iteration":588,"passed_time":3.229294827,"remaining_time":2.253378903},
{"learn":[3.74417648],"iteration":589,"passed_time":3.231011827,"remaining_time":2.245279405},
{"learn":[3.738788389],"iteration":590,"passed_time":3.232071502,"remaining_time":2.236746607},
{"learn":[3.736021611],"iteration":591,"passed_time":3.23304442,"remaining_time":2.228179262},
{"learn":[3.734546151],"iteration":592,"passed_time":3.23433111,"remaining_time":2.219852886},
{"learn":[3.733527479],"iteration":593,"passed_time":3.241858484,"remaining_time":2.215815732},
{"learn":[3.733026392],"iteration":594,"passed_time":3.24287033,"remaining_time":2.207331906},
{"learn":[3.730314752],"iteration":595,"passed_time":3.243816368,"remaining_time":2.198828545},
{"learn":[3.727342596],"iteration":596,"passed_time":3.244735557,"remaining_time":2.190332378},
{"learn":[3.725459604],"iteration":597,"passed_time":3.245959938,"remaining_time":2.182066714},
{"learn":[3.723158842],"iteration":598,"passed_time":3.246915596,"remaining_time":2.173644664},
{"learn":[3.722362756],"iteration":599,"passed_time":3.252882437,"remaining_time":2.168588291},
{"learn":[3.721443615],"iteration":600,"passed_time":3.253872484,"remaining_time":2.160224827},
{"learn":[3.720743486],"iteration":601,"passed_time":3.254674245,"remaining_time":2.151761378},
{"learn":[3.720215334],"iteration":602,"passed_time":3.255900216,"remaining_time":2.14360263},
{"learn":[3.719436563],"iteration":603,"passed_time":3.257517169,"remaining_time":2.135723177},
{"learn":[3.715046574],"iteration":604,"passed_time":3.258483976,"remaining_time":2.127439951},
{"learn":[3.71443396],"iteration":605,"passed_time":3.259404905,"remaining_time":2.119151044},
{"learn":[3.712938941],"iteration":606,"passed_time":3.310454413,"remaining_time":2.143341984},
{"learn":[3.712814764],"iteration":607,"passed_time":3.311585287,"remaining_time":2.13510104},
{"learn":[3.71235348],"iteration":608,"passed_time":3.312699591,"remaining_time":2.126872808},
{"learn":[3.711223749],"iteration":609,"passed_time":3.313668168,"remaining_time":2.11857473},
{"learn":[3.710755648],"iteration":610,"passed_time":3.314600376,"remaining_time":2.11027749},
{"learn":[3.708668039],"iteration":611,"passed_time":3.363829478,"remaining_time":2.132623917},
{"learn":[3.705623591],"iteration":612,"passed_time":3.364690487,"remaining_time":2.124201009},
{"learn":[3.704045802],"iteration":613,"passed_time":3.365537648,"remaining_time":2.115794026},
{"learn":[3.699915209],"iteration":614,"passed_time":3.366382888,"remaining_time":2.107410426},
{"learn":[3.696182221],"iteration":615,"passed_time":3.367923702,"remaining_time":2.099484905},
{"learn":[3.694263278],"iteration":616,"passed_time":3.403430413,"remaining_time":2.11266426},
{"learn":[3.693810229],"iteration":617,"passed_time":3.406343525,"remaining_time":2.105539202},
{"learn":[3.690900932],"iteration":618,"passed_time":3.407366812,"remaining_time":2.097264548},
{"learn":[3.688020895],"iteration":619,"passed_time":3.40830316,"remaining_time":2.088960001},
{"learn":[3.685491894],"iteration":620,"passed_time":3.409224348,"remaining_time":2.080669932},
{"learn":[3.684328128],"iteration":621,"passed_time":3.531063315,"remaining_time":2.145887352},
{"learn":[3.680640153],"iteration":622,"passed_time":3.532003813,"remaining_time":2.137344201},
{"learn":[3.678932783],"iteration":623,"passed_time":3.53299059,"remaining_time":2.128853304},
{"learn":[3.674167041],"iteration":624,"passed_time":3.538273637,"remaining_time":2.122964182},
{"learn":[3.672200976],"iteration":625,"passed_time":3.539455049,"remaining_time":2.114626499},
{"learn":[3.670606604],"iteration":626,"passed_time":3.540392157,"remaining_time":2.106166307},
{"learn":[3.665506042],"iteration":627,"passed_time":3.542782031,"remaining_time":2.09859063},
{"learn":[3.664214007],"iteration":628,"passed_time":3.54370709,"remaining_time":2.090167457},
{"learn":[3.66261643],"iteration":629,"passed_time":3.544579839,"remaining_time":2.081737366},
{"learn":[3.662118449],"iteration":630,"passed_time":3.554059388,"remaining_time":2.078364365},
{"learn":[3.660871366],"iteration":631,"passed_time":3.555037195,"remaining_time":2.070021658},
{"learn":[3.656695243],"iteration":632,"passed_time":3.556028342,"remaining_time":2.061709955},
{"learn":[3.654497801],"iteration":633,"passed_time":3.557510208,"remaining_time":2.053704631},
{"learn":[3.654189134],"iteration":634,"passed_time":3.558491725,"remaining_time":2.045432251},
{"learn":[3.653957699],"iteration":635,"passed_time":3.559383554,"remaining_time":2.037131468},
{"learn":[3.651920725],"iteration":636,"passed_time":3.560505518,"remaining_time":2.028985091},
{"learn":[3.65106705],"iteration":637,"passed_time":3.561529514,"remaining_time":2.020805147},
{"learn":[3.650612844],"iteration":638,"passed_time":3.562380724,"remaining_time":2.012549986},
{"learn":[3.649884732],"iteration":639,"passed_time":3.563324172,"remaining_time":2.004369847},
{"learn":[3.646276182],"iteration":640,"passed_time":3.564329208,"remaining_time":1.99624678},
{"learn":[3.645808194],"iteration":641,"passed_time":3.565175129,"remaining_time":1.988057159},
{"learn":[3.645042989],"iteration":642,"passed_time":3.566060398,"remaining_time":1.979912227},
{"learn":[3.639864499],"iteration":643,"passed_time":3.567894725,"remaining_time":1.972314475},
{"learn":[3.637318478],"iteration":644,"passed_time":3.568804604,"remaining_time":1.96422579},
{"learn":[3.636344905],"iteration":645,"passed_time":3.569675944,"remaining_time":1.956138211},
{"learn":[3.634754643],"iteration":646,"passed_time":3.57113417,"remaining_time":1.94839314},
{"learn":[3.630724975],"iteration":647,"passed_time":3.572194045,"remaining_time":1.940451086},
{"learn":[3.629408252],"iteration":648,"passed_time":3.638438349,"remaining_time":1.967784069},
{"learn":[3.62790646],"iteration":649,"passed_time":3.639612862,"remaining_time":1.959791541},
{"learn":[3.627388973],"iteration":650,"passed_time":3.641082397,"remaining_time":1.951978121},
{"learn":[3.625163557],"iteration":651,"passed_time":3.642063454,"remaining_time":1.943923439},
{"learn":[3.623701985],"iteration":652,"passed_time":3.67567147,"remaining_time":1.953228178},
{"learn":[3.622342639],"iteration":653,"passed_time":3.676822293,"remaining_time":1.945230143},
{"learn":[3.621130639],"iteration":654,"passed_time":3.679154189,"remaining_time":1.937875107},
{"learn":[3.619125665],"iteration":655,"passed_time":3.720143242,"remaining_time":1.950806822},
{"learn":[3.618878783],"iteration":656,"passed_time":3.721340074,"remaining_time":1.942800069},
{"learn":[3.616207429],"iteration":657,"passed_time":3.722240203,"remaining_time":1.934659802},
{"learn":[3.61206486],"iteration":658,"passed_time":3.739600838,"remaining_time":1.935059007},
{"learn":[3.611955873],"iteration":659,"passed_time":3.740454438,"remaining_time":1.926900771},
{"learn":[3.610713743],"iteration":660,"passed_time":3.741483494,"remaining_time":1.918854621},
{"learn":[3.610044025],"iteration":661,"passed_time":3.742553539,"remaining_time":1.910850599},
{"learn":[3.607342669],"iteration":662,"passed_time":3.74339031,"remaining_time":1.902748921},
{"learn":[3.602510618],"iteration":663,"passed_time":3.74425377,"remaining_time":1.89468263},
{"learn":[3.600492392],"iteration":664,"passed_time":3.745492751,"remaining_time":1.886827175},
{"learn":[3.597171065],"iteration":665,"passed_time":3.74636616,"remaining_time":1.878808255},
{"learn":[3.594358798],"iteration":666,"passed_time":3.747196391,"remaining_time":1.870789203},
{"learn":[3.593945251],"iteration":667,"passed_time":3.748306375,"remaining_time":1.862930713},
{"learn":[3.593607748],"iteration":668,"passed_time":3.749542346,"remaining_time":1.855154733},
{"learn":[3.592238714],"iteration":669,"passed_time":3.750468024,"remaining_time":1.847245445},
{"learn":[3.590144654],"iteration":670,"passed_time":3.751353344,"remaining_time":1.839337183},
{"learn":[3.587151536],"iteration":671,"passed_time":3.752565246,"remaining_time":1.831609227},
{"learn":[3.586070865],"iteration":672,"passed_time":3.753439565,"remaining_time":1.823736609},
{"learn":[3.585102746],"iteration":673,"passed_time":3.754238856,"remaining_time":1.815848468},
{"learn":[3.584362847],"iteration":674,"passed_time":3.755492927,"remaining_time":1.808200298},
{"learn":[3.581407561],"iteration":675,"passed_time":3.756593132,"remaining_time":1.8004973},
{"learn":[3.57919422],"iteration":676,"passed_time":3.76610532,"remaining_time":1.796827206},
{"learn":[3.577632204],"iteration":677,"passed_time":3.767078987,"remaining_time":1.789084711},
{"learn":[3.573911195],"iteration":678,"passed_time":3.768011475,"remaining_time":1.781342686},
{"learn":[3.573408216],"iteration":679,"passed_time":3.76908795,"remaining_time":1.773688447},
{"learn":[3.571076482],"iteration":680,"passed_time":3.770180744,"remaining_time":1.766061171},
{"learn":[3.568177107],"iteration":681,"passed_time":3.7712159,"remaining_time":1.758426182},
{"learn":[3.564824621],"iteration":682,"passed_time":3.778060111,"remaining_time":1.753506669},
{"learn":[3.562475026],"iteration":683,"passed_time":3.779023198,"remaining_time":1.745864518},
{"learn":[3.561226889],"iteration":684,"passed_time":3.779948347,"remaining_time":1.738224422},
{"learn":[3.559383467],"iteration":685,"passed_time":3.781003592,"remaining_time":1.730663452},
{"learn":[3.555209766],"iteration":686,"passed_time":3.788873558,"remaining_time":1.726226235},
{"learn":[3.55345383],"iteration":687,"passed_time":3.789873805,"remaining_time":1.718663702},
{"learn":[3.552300968],"iteration":688,"passed_time":3.791468798,"remaining_time":1.711388674},
{"learn":[3.551253986],"iteration":689,"passed_time":3.792918204,"remaining_time":1.7040647},
{"learn":[3.549807725],"iteration":690,"passed_time":3.794181374,"remaining_time":1.69667445},
{"learn":[3.547992926],"iteration":691,"passed_time":3.795271179,"remaining_time":1.689224744},
{"learn":[3.545438607],"iteration":692,"passed_time":3.796366203,"remaining_time":1.681795706},
{"learn":[3.543313763],"iteration":693,"passed_time":3.798313168,"remaining_time":1.674760561},
{"learn":[3.542962896],"iteration":694,"passed_time":3.800003308,"remaining_time":1.667627351},
{"learn":[3.539800465],"iteration":695,"passed_time":3.801036804,"remaining_time":1.660222972},
{"learn":[3.53953187],"iteration":696,"passed_time":3.801996202,"remaining_time":1.652804662},
{"learn":[3.536332425],"iteration":697,"passed_time":3.805202677,"remaining_time":1.64637709},
{"learn":[3.534993327],"iteration":698,"passed_time":3.80636447,"remaining_time":1.639078262},
{"learn":[3.531637011],"iteration":699,"passed_time":3.807403046,"remaining_time":1.631744162},
{"learn":[3.531040284],"iteration":700,"passed_time":3.808360573,"remaining_time":1.624393454},
{"learn":[3.529973872],"iteration":701,"passed_time":3.809510677,"remaining_time":1.617142709},
{"learn":[3.527325183],"iteration":702,"passed_time":3.810587671,"remaining_time":1.609878433},
{"learn":[3.527200815],"iteration":703,"passed_time":3.81152433,"remaining_time":1.602572729},
{"learn":[3.523459911],"iteration":704,"passed_time":3.816455235,"remaining_time":1.596956446},
{"learn":[3.522729934],"iteration":705,"passed_time":3.817330714,"remaining_time":1.5896533},
{"learn":[3.522260582],"iteration":706,"passed_time":3.818158355,"remaining_time":1.582348512},
{"learn":[3.518641591],"iteration":707,"passed_time":3.819518723,"remaining_time":1.575281733},
{"learn":[3.516856405],"iteration":708,"passed_time":3.820578628,"remaining_time":1.56810773},
{"learn":[3.515083413],"iteration":709,"passed_time":3.821630804,"remaining_time":1.560947793},
{"learn":[3.514671214],"iteration":710,"passed_time":3.822454905,"remaining_time":1.553712331},
{"learn":[3.512617621],"iteration":711,"passed_time":3.823255006,"remaining_time":1.546485171},
{"learn":[3.510747971],"iteration":712,"passed_time":3.824067687,"remaining_time":1.539281103},
{"learn":[3.508149266],"iteration":713,"passed_time":3.825346757,"remaining_time":1.532281754},
{"learn":[3.504557165],"iteration":714,"passed_time":3.826364123,"remaining_time":1.525194091},
{"learn":[3.501367208],"iteration":715,"passed_time":3.827463418,"remaining_time":1.518155881},
{"learn":[3.497593362],"iteration":716,"passed_time":3.828427605,"remaining_time":1.51108091},
{"learn":[3.496291169],"iteration":717,"passed_time":3.829579898,"remaining_time":1.50409684},
{"learn":[3.49330374],"iteration":718,"passed_time":3.83079825,"remaining_time":1.49715481},
{"learn":[3.490044385],"iteration":719,"passed_time":3.832034711,"remaining_time":1.490235721},
{"learn":[3.488891789],"iteration":720,"passed_time":3.833054307,"remaining_time":1.483248477},
{"learn":[3.486869081],"iteration":721,"passed_time":3.834434355,"remaining_time":1.476416552},
{"learn":[3.486303638],"iteration":722,"passed_time":3.8355009,"remaining_time":1.469479598},
{"learn":[3.486035862],"iteration":723,"passed_time":3.836627604,"remaining_time":1.462581794},
{"learn":[3.482668951],"iteration":724,"passed_time":3.83765665,"remaining_time":1.455662867},
{"learn":[3.47820549],"iteration":725,"passed_time":3.838879261,"remaining_time":1.44883322},
{"learn":[3.474392283],"iteration":726,"passed_time":3.83979792,"remaining_time":1.441904858},
{"learn":[3.472268163],"iteration":727,"passed_time":3.840872845,"remaining_time":1.435051393},
{"learn":[3.471209164],"iteration":728,"passed_time":3.841737325,"remaining_time":1.428135549},
{"learn":[3.470049971],"iteration":729,"passed_time":3.842535066,"remaining_time":1.4212116},
{"learn":[3.469078654],"iteration":730,"passed_time":3.843482464,"remaining_time":1.414359484},
{"learn":[3.468643292],"iteration":731,"passed_time":3.844561649,"remaining_time":1.407571751},
{"learn":[3.468134848],"iteration":732,"passed_time":3.845497037,"remaining_time":1.400747215},
{"learn":[3.467820182],"iteration":733,"passed_time":3.846393916,"remaining_time":1.393924771},
{"learn":[3.465776156],"iteration":734,"passed_time":3.847477051,"remaining_time":1.387185603},
{"learn":[3.463037608],"iteration":735,"passed_time":3.84837878,"remaining_time":1.380396736},
{"learn":[3.45965637],"iteration":736,"passed_time":3.849278269,"remaining_time":1.373623046},
{"learn":[3.457275091],"iteration":737,"passed_time":3.850587378,"remaining_time":1.367010695},
{"learn":[3.455522955],"iteration":738,"passed_time":3.851556015,"remaining_time":1.360292449},
{"learn":[3.451270508],"iteration":739,"passed_time":3.852611481,"remaining_time":1.35362025},
{"learn":[3.450978947],"iteration":740,"passed_time":3.853594358,"remaining_time":1.346937839},
{"learn":[3.450608492],"iteration":741,"passed_time":3.854475397,"remaining_time":1.340235381},
{"learn":[3.448122004],"iteration":742,"passed_time":3.863695112,"remaining_time":1.336432899},
{"learn":[3.445646714],"iteration":743,"passed_time":3.864593201,"remaining_time":1.329752499},
{"learn":[3.44411263],"iteration":744,"passed_time":3.86548682,"remaining_time":1.323086093},
{"learn":[3.443264164],"iteration":745,"passed_time":3.866530526,"remaining_time":1.316486265},
{"learn":[3.439521363],"iteration":746,"passed_time":3.867433665,"remaining_time":1.309853704},
{"learn":[3.436809225],"iteration":747,"passed_time":3.868372333,"remaining_time":1.303248433},
{"learn":[3.435509465],"iteration":748,"passed_time":3.870326877,"remaining_time":1.296998727},
{"learn":[3.434450277],"iteration":749,"passed_time":3.871373693,"remaining_time":1.290457898},
{"learn":[3.431786753],"iteration":750,"passed_time":3.872915867,"remaining_time":1.28409594},
{"learn":[3.430150302],"iteration":751,"passed_time":3.874226186,"remaining_time":1.277670338},
{"learn":[3.42696281],"iteration":752,"passed_time":3.875505906,"remaining_time":1.271248285},
{"learn":[3.426870334],"iteration":753,"passed_time":3.876455214,"remaining_time":1.264732073},
{"learn":[3.425200309],"iteration":754,"passed_time":3.877376053,"remaining_time":1.258221368},
{"learn":[3.423383783],"iteration":755,"passed_time":3.8792043,"remaining_time":1.252018319},
{"learn":[3.422752979],"iteration":756,"passed_time":3.92376092,"remaining_time":1.259542805},
{"learn":[3.420845924],"iteration":757,"passed_time":3.937269305,"remaining_time":1.257017377},
{"learn":[3.418917862],"iteration":758,"passed_time":3.938274772,"remaining_time":1.250493043},
{"learn":[3.417095735],"iteration":759,"passed_time":3.93919633,"remaining_time":1.243956736},
{"learn":[3.414391848],"iteration":760,"passed_time":4.040227652,"remaining_time":1.268875702},
{"learn":[3.41426711],"iteration":761,"passed_time":4.04118849,"remaining_time":1.262208478},
{"learn":[3.411976013],"iteration":762,"passed_time":4.042325073,"remaining_time":1.255610803},
{"learn":[3.408614844],"iteration":763,"passed_time":4.076407948,"remaining_time":1.259204549},
{"learn":[3.407906721],"iteration":764,"passed_time":4.077813715,"remaining_time":1.252661729},
{"learn":[3.407494015],"iteration":765,"passed_time":4.079571224,"remaining_time":1.246239773},
{"learn":[3.406287128],"iteration":766,"passed_time":4.080684878,"remaining_time":1.239634389},
{"learn":[3.404600442],"iteration":767,"passed_time":4.08360997,"remaining_time":1.233590512},
{"learn":[3.404012662],"iteration":768,"passed_time":4.084837941,"remaining_time":1.227044947},
{"learn":[3.400398762],"iteration":769,"passed_time":4.086044663,"remaining_time":1.220506847},
{"learn":[3.399737714],"iteration":770,"passed_time":4.087077699,"remaining_time":1.21393099},
{"learn":[3.399185251],"iteration":771,"passed_time":4.088183093,"remaining_time":1.207390862},
{"learn":[3.397245411],"iteration":772,"passed_time":4.0900247,"remaining_time":1.201080992},
{"learn":[3.396229831],"iteration":773,"passed_time":4.090992648,"remaining_time":1.194527569},
{"learn":[3.394002836],"iteration":774,"passed_time":4.091880757,"remaining_time":1.187965381},
{"learn":[3.389617243],"iteration":775,"passed_time":4.093188616,"remaining_time":1.181538982},
{"learn":[3.385426488],"iteration":776,"passed_time":4.094246542,"remaining_time":1.175054027},
{"learn":[3.385072258],"iteration":777,"passed_time":4.116015524,"remaining_time":1.174492861},
{"learn":[3.383842366],"iteration":778,"passed_time":4.117195926,"remaining_time":1.168036328},
{"learn":[3.380110746],"iteration":779,"passed_time":4.11829542,"remaining_time":1.161570503},
{"learn":[3.378595218],"iteration":780,"passed_time":4.11919088,"remaining_time":1.155061207},
{"learn":[3.377371219],"iteration":781,"passed_time":4.175612183,"remaining_time":1.16404534},
{"learn":[3.375814782],"iteration":782,"passed_time":4.176781676,"remaining_time":1.157549966},
{"learn":[3.374195887],"iteration":783,"passed_time":4.177916149,"remaining_time":1.151058531},
{"learn":[3.373704309],"iteration":784,"passed_time":4.179014203,"remaining_time":1.144570769},
{"learn":[3.372971757],"iteration":785,"passed_time":4.180096018,"remaining_time":1.1380923},
{"learn":[3.371565136],"iteration":786,"passed_time":4.180968398,"remaining_time":1.131570862},
{"learn":[3.3700309],"iteration":787,"passed_time":4.181793689,"remaining_time":1.125051094},
{"learn":[3.368186663],"iteration":788,"passed_time":4.187216822,"remaining_time":1.119775348},
{"learn":[3.366710398],"iteration":789,"passed_time":4.188185489,"remaining_time":1.11331513},
{"learn":[3.364598042],"iteration":790,"passed_time":4.189143057,"remaining_time":1.106865865},
{"learn":[3.36348442],"iteration":791,"passed_time":4.190329749,"remaining_time":1.100490641},
{"learn":[3.362001759],"iteration":792,"passed_time":4.191260498,"remaining_time":1.094061694},
{"learn":[3.361580401],"iteration":793,"passed_time":4.192490969,"remaining_time":1.087724357},
{"learn":[3.359543675],"iteration":794,"passed_time":4.193338779,"remaining_time":1.081301195},
{"learn":[3.35766119],"iteration":795,"passed_time":4.194306717,"remaining_time":1.074922827},
{"learn":[3.354592969],"iteration":796,"passed_time":4.199775509,"remaining_time":1.069704427},
{"learn":[3.350985986],"iteration":797,"passed_time":4.200869123,"remaining_time":1.063377898},
{"learn":[3.349589624],"iteration":798,"passed_time":4.202041756,"remaining_time":1.057084347},
{"learn":[3.349110856],"iteration":799,"passed_time":4.203011893,"remaining_time":1.050752973},
{"learn":[3.345315441],"iteration":800,"passed_time":4.274186842,"remaining_time":1.061876631},
{"learn":[3.34397474],"iteration":801,"passed_time":4.275396114,"remaining_time":1.055521734},
{"learn":[3.343800902],"iteration":802,"passed_time":4.276327222,"remaining_time":1.049111411},
{"learn":[3.342329465],"iteration":803,"passed_time":4.277414017,"remaining_time":1.042752671},
{"learn":[3.34220347],"iteration":804,"passed_time":4.278706447,"remaining_time":1.036456841},
{"learn":[3.341279219],"iteration":805,"passed_time":4.291461369,"remaining_time":1.032932389},
{"learn":[3.337329521],"iteration":806,"passed_time":4.292784588,"remaining_time":1.026651085},
{"learn":[3.336708453],"iteration":807,"passed_time":4.293876963,"remaining_time":1.020327199},
{"learn":[3.333252703],"iteration":808,"passed_time":4.29483455,"remaining_time":1.013984424},
{"learn":[3.332186769],"iteration":809,"passed_time":4.295963064,"remaining_time":1.00769504},
{"learn":[3.330594851],"iteration":810,"passed_time":4.296890982,"remaining_time":1.001371635},
{"learn":[3.327867442],"iteration":811,"passed_time":4.297823841,"remaining_time":0.9950626626},
{"learn":[3.327563111],"iteration":812,"passed_time":4.298907665,"remaining_time":0.9888016401},
{"learn":[3.326308994],"iteration":813,"passed_time":4.336325962,"remaining_time":0.9908558095},
{"learn":[3.326249879],"iteration":814,"passed_time":4.337466846,"remaining_time":0.9845783637},
{"learn":[3.322336238],"iteration":815,"passed_time":4.338625809,"remaining_time":0.9783175843},
{"learn":[3.320491154],"iteration":816,"passed_time":4.339667554,"remaining_time":0.9720430385},
{"learn":[3.320434271],"iteration":817,"passed_time":4.365024552,"remaining_time":0.9711912818},
{"learn":[3.319609638],"iteration":818,"passed_time":4.366235654,"remaining_time":0.9649434108},
{"learn":[3.316182682],"iteration":819,"passed_time":4.367351078,"remaining_time":0.958686822},
{"learn":[3.313126612],"iteration":820,"passed_time":4.368456852,"remaining_time":0.9524406536},
{"learn":[3.311222803],"iteration":821,"passed_time":4.369652394,"remaining_time":0.9462264309},
{"learn":[3.309627335],"iteration":822,"passed_time":4.370643201,"remaining_time":0.9399803726},
{"learn":[3.307974895],"iteration":823,"passed_time":4.376176262,"remaining_time":0.9347172599},
{"learn":[3.307321505],"iteration":824,"passed_time":4.377299696,"remaining_time":0.9285181173},
{"learn":[3.306759087],"iteration":825,"passed_time":4.378388401,"remaining_time":0.9223239488},
{"learn":[3.30484037],"iteration":826,"passed_time":4.438347231,"remaining_time":0.9284571596},
{"learn":[3.30201994],"iteration":827,"passed_time":4.439368817,"remaining_time":0.9221877254},
{"learn":[3.299302297],"iteration":828,"passed_time":4.440295836,"remaining_time":0.915911445},
{"learn":[3.298132671],"iteration":829,"passed_time":4.441445569,"remaining_time":0.9096936708},
{"learn":[3.296976183],"iteration":830,"passed_time":4.442420946,"remaining_time":0.9034526353},
{"learn":[3.293144745],"iteration":831,"passed_time":4.443648678,"remaining_time":0.8972752137},
{"learn":[3.290284404],"iteration":832,"passed_time":4.444677654,"remaining_time":0.8910698297},
{"learn":[3.288285745],"iteration":833,"passed_time":4.446198048,"remaining_time":0.8849746714},
{"learn":[3.286662667],"iteration":834,"passed_time":4.447216504,"remaining_time":0.8787912853},
{"learn":[3.285692682],"iteration":835,"passed_time":4.448134153,"remaining_time":0.8726004798},
{"learn":[3.284565611],"iteration":836,"passed_time":4.449752285,"remaining_time":0.8665586887},
{"learn":[3.283897383],"iteration":837,"passed_time":4.492949647,"remaining_time":0.8685654449},
{"learn":[3.280712855],"iteration":838,"passed_time":4.494069531,"remaining_time":0.8623899815},
{"learn":[3.280468341],"iteration":839,"passed_time":4.494987349,"remaining_time":0.8561880666},
{"learn":[3.277814895],"iteration":840,"passed_time":4.495959697,"remaining_time":0.8500090271},
{"learn":[3.276316385],"iteration":841,"passed_time":4.497016182,"remaining_time":0.8438581434},
{"learn":[3.27557063],"iteration":842,"passed_time":4.497855453,"remaining_time":0.8376788921},
{"learn":[3.27499628],"iteration":843,"passed_time":4.498672643,"remaining_time":0.8315082137},
{"learn":[3.273569958],"iteration":844,"passed_time":4.500181928,"remaining_time":0.8254771584},
{"learn":[3.269665595],"iteration":845,"passed_time":4.501861559,"remaining_time":0.8194878015},
{"learn":[3.267984685],"iteration":846,"passed_time":4.503226457,"remaining_time":0.8134517685},
{"learn":[3.267702508],"iteration":847,"passed_time":4.504349061,"remaining_time":0.8073833223},
{"learn":[3.266671924],"iteration":848,"passed_time":4.505532813,"remaining_time":0.8013374026},
{"learn":[3.265359825],"iteration":849,"passed_time":4.506499831,"remaining_time":0.795264676},
{"learn":[3.2618983],"iteration":850,"passed_time":4.507600395,"remaining_time":0.7892273312},
{"learn":[3.260456253],"iteration":851,"passed_time":4.576184575,"remaining_time":0.794924081},
{"learn":[3.258389147],"iteration":852,"passed_time":4.57723492,"remaining_time":0.7888083625},
{"learn":[3.258108469],"iteration":853,"passed_time":4.583911454,"remaining_time":0.783666361},
{"learn":[3.256424936],"iteration":854,"passed_time":4.585017638,"remaining_time":0.7775760907},
{"learn":[3.254817983],"iteration":855,"passed_time":4.586322368,"remaining_time":0.7715308656},
{"learn":[3.253898449],"iteration":856,"passed_time":4.587366324,"remaining_time":0.7654531905},
{"learn":[3.253023652],"iteration":857,"passed_time":4.588732082,"remaining_time":0.7594405077},
{"learn":[3.252845542],"iteration":858,"passed_time":4.590198368,"remaining_time":0.7534551453},
{"learn":[3.252316026],"iteration":859,"passed_time":4.591006099,"remaining_time":0.7473730858},
{"learn":[3.24975301],"iteration":860,"passed_time":4.59181093,"remaining_time":0.7413028098},
{"learn":[3.249151075],"iteration":861,"passed_time":4.596544809,"remaining_time":0.735873763},
{"learn":[3.246257135],"iteration":862,"passed_time":4.597505527,"remaining_time":0.7298473432},
{"learn":[3.243826471],"iteration":863,"passed_time":4.598299218,"remaining_time":0.7238063585},
{"learn":[3.243190653],"iteration":864,"passed_time":4.59910742,"remaining_time":0.7177797707},
{"learn":[3.24008797],"iteration":865,"passed_time":4.600017778,"remaining_time":0.7117810419},
{"learn":[3.240036811],"iteration":866,"passed_time":4.601023035,"remaining_time":0.7058086086},
{"learn":[3.238676314],"iteration":867,"passed_time":4.601954713,"remaining_time":0.699836431},
{"learn":[3.237848782],"iteration":868,"passed_time":4.602868612,"remaining_time":0.6938731739},
{"learn":[3.236405498],"iteration":869,"passed_time":4.604916814,"remaining_time":0.6880910182},
{"learn":[3.233378068],"iteration":870,"passed_time":4.60593534,"remaining_time":0.6821649356},
{"learn":[3.233169169],"iteration":871,"passed_time":4.606853309,"remaining_time":0.6762353481},
{"learn":[3.232434885],"iteration":872,"passed_time":4.616414396,"remaining_time":0.6715746028},
{"learn":[3.229978115],"iteration":873,"passed_time":4.617473211,"remaining_time":0.665676916},
{"learn":[3.229648848],"iteration":874,"passed_time":4.618532196,"remaining_time":0.6597903138},
{"learn":[3.227208761],"iteration":875,"passed_time":4.61966451,"remaining_time":0.6539251133},
{"learn":[3.226258869],"iteration":876,"passed_time":4.620851802,"remaining_time":0.6480784169},
{"learn":[3.225331995],"iteration":877,"passed_time":4.621892618,"remaining_time":0.6422219811},
{"learn":[3.221968268],"iteration":878,"passed_time":4.622872275,"remaining_time":0.6363680834},
{"learn":[3.221166317],"iteration":879,"passed_time":4.625308428,"remaining_time":0.6307238766},
{"learn":[3.220047503],"iteration":880,"passed_time":4.626335074,"remaining_time":0.6248965651},
{"learn":[3.21982781],"iteration":881,"passed_time":4.627456248,"remaining_time":0.619092786},
{"learn":[3.216693405],"iteration":882,"passed_time":4.628787867,"remaining_time":0.6133274977},
{"learn":[3.214798761],"iteration":883,"passed_time":4.629812853,"remaining_time":0.6075320033},
{"learn":[3.214395085],"iteration":884,"passed_time":4.630911617,"remaining_time":0.6017568768},
{"learn":[3.213470696],"iteration":885,"passed_time":4.631772197,"remaining_time":0.5959616597},
{"learn":[3.211595017],"iteration":886,"passed_time":4.63295784,"remaining_time":0.5902189807},
{"learn":[3.210965255],"iteration":887,"passed_time":4.633925737,"remaining_time":0.584459102},
{"learn":[3.209413583],"iteration":888,"passed_time":4.635004672,"remaining_time":0.5787238679},
{"learn":[3.208331683],"iteration":889,"passed_time":4.63595918,"remaining_time":0.5729837188},
{"learn":[3.207110711],"iteration":890,"passed_time":4.636845549,"remaining_time":0.5672459762},
{"learn":[3.204519413],"iteration":891,"passed_time":4.638364703,"remaining_time":0.5615957264},
{"learn":[3.201421296],"iteration":892,"passed_time":4.639490987,"remaining_time":0.5559076547},
{"learn":[3.200691259],"iteration":893,"passed_time":4.641150708,"remaining_time":0.550293037},
{"learn":[3.200485067],"iteration":894,"passed_time":4.704139518,"remaining_time":0.5518822899},
{"learn":[3.197467568],"iteration":895,"passed_time":4.705144765,"remaining_time":0.5461328745},
{"learn":[3.195838544],"iteration":896,"passed_time":4.706256739,"remaining_time":0.5404062922},
{"learn":[3.195671746],"iteration":897,"passed_time":4.759991585,"remaining_time":0.5406671956},
{"learn":[3.194213094],"iteration":898,"passed_time":4.761193667,"remaining_time":0.5349060738},
{"learn":[3.192884691],"iteration":899,"passed_time":4.762182604,"remaining_time":0.5291314004},
{"learn":[3.188364239],"iteration":900,"passed_time":4.763154061,"remaining_time":0.5233654296},
{"learn":[3.185219478],"iteration":901,"passed_time":4.804811769,"remaining_time":0.522030547},
{"learn":[3.184120387],"iteration":902,"passed_time":4.810206133,"remaining_time":0.5167109578},
{"learn":[3.183725321],"iteration":903,"passed_time":4.8111799,"remaining_time":0.5109217593},
{"learn":[3.181264554],"iteration":904,"passed_time":4.812182457,"remaining_time":0.5051462248},
{"learn":[3.180741589],"iteration":905,"passed_time":4.831867498,"remaining_time":0.5013195858},
{"learn":[3.179782639],"iteration":906,"passed_time":4.832886724,"remaining_time":0.4955440632},
{"learn":[3.176377564],"iteration":907,"passed_time":4.833967469,"remaining_time":0.4897852501},
{"learn":[3.174078182],"iteration":908,"passed_time":4.835233599,"remaining_time":0.4840552888},
{"learn":[3.171242379],"iteration":909,"passed_time":4.836209766,"remaining_time":0.4783064604},
{"learn":[3.170421012],"iteration":910,"passed_time":4.837135425,"remaining_time":0.4725631754},
{"learn":[3.170087224],"iteration":911,"passed_time":4.838225979,"remaining_time":0.4668463664},
{"learn":[3.167303059],"iteration":912,"passed_time":4.839163337,"remaining_time":0.4611250935},
{"learn":[3.16705966],"iteration":913,"passed_time":4.8403569,"remaining_time":0.4554383954},
{"learn":[3.165667683],"iteration":914,"passed_time":4.841302277,"remaining_time":0.4497384629},
{"learn":[3.164689733],"iteration":915,"passed_time":4.842507599,"remaining_time":0.4440727493},
{"learn":[3.163311455],"iteration":916,"passed_time":4.865752317,"remaining_time":0.4404116056},
{"learn":[3.159425016],"iteration":917,"passed_time":4.866839831,"remaining_time":0.4347286124},
{"learn":[3.159327058],"iteration":918,"passed_time":4.867804579,"remaining_time":0.4290447997},
{"learn":[3.15819426],"iteration":919,"passed_time":4.86903809,"remaining_time":0.4233946165},
{"learn":[3.157086603],"iteration":920,"passed_time":4.904061693,"remaining_time":0.4206524145},
{"learn":[3.153354154],"iteration":921,"passed_time":4.904968422,"remaining_time":0.4149539446},
{"learn":[3.153261317],"iteration":922,"passed_time":4.906981245,"remaining_time":0.409358132},
{"learn":[3.153168454],"iteration":923,"passed_time":4.913651369,"remaining_time":0.4041531429},
{"learn":[3.152080399],"iteration":924,"passed_time":4.914848481,"remaining_time":0.3985012282},
{"learn":[3.151635144],"iteration":925,"passed_time":4.915974415,"remaining_time":0.392853247},
{"learn":[3.147762655],"iteration":926,"passed_time":4.916981801,"remaining_time":0.3872056866},
{"learn":[3.147172317],"iteration":927,"passed_time":4.91916305,"remaining_time":0.3816592022},
{"learn":[3.146254125],"iteration":928,"passed_time":4.92001792,"remaining_time":0.3760185924},
{"learn":[3.144869828],"iteration":929,"passed_time":4.924863977,"remaining_time":0.3706886865},
{"learn":[3.143466218],"iteration":930,"passed_time":4.926012211,"remaining_time":0.36508576},
{"learn":[3.141919643],"iteration":931,"passed_time":4.927225352,"remaining_time":0.3594971287},
{"learn":[3.141054135],"iteration":932,"passed_time":4.928354116,"remaining_time":0.3539118175},
{"learn":[3.139390417],"iteration":933,"passed_time":4.929309594,"remaining_time":0.3483238043},
{"learn":[3.139025283],"iteration":934,"passed_time":4.931480843,"remaining_time":0.342830219},
{"learn":[3.137824183],"iteration":935,"passed_time":4.932430461,"remaining_time":0.3372602024},
{"learn":[3.135620453],"iteration":936,"passed_time":4.933612093,"remaining_time":0.3317156477},
{"learn":[3.13443178],"iteration":937,"passed_time":4.934579691,"remaining_time":0.3261662482},
{"learn":[3.132765713],"iteration":938,"passed_time":4.935501439,"remaining_time":0.3206236292},
{"learn":[3.131434124],"iteration":939,"passed_time":4.940781156,"remaining_time":0.31536901},
{"learn":[3.128384262],"iteration":940,"passed_time":4.941837771,"remaining_time":0.3098495521},
{"learn":[3.128120455],"iteration":941,"passed_time":4.942843538,"remaining_time":0.3043364386},
{"learn":[3.126314615],"iteration":942,"passed_time":4.943861544,"remaining_time":0.2988336246},
{"learn":[3.125409666],"iteration":943,"passed_time":4.944753623,"remaining_time":0.2933328421},
{"learn":[3.123072589],"iteration":944,"passed_time":4.945598663,"remaining_time":0.2878390757},
{"learn":[3.122921099],"iteration":945,"passed_time":4.954538095,"remaining_time":0.2828171851},
{"learn":[3.122182662],"iteration":946,"passed_time":4.95561748,"remaining_time":0.277347124},
{"learn":[3.120040951],"iteration":947,"passed_time":4.956593017,"remaining_time":0.2718806296},
{"learn":[3.118767799],"iteration":948,"passed_time":4.957867637,"remaining_time":0.2664396728},
{"learn":[3.118203218],"iteration":949,"passed_time":4.968959638,"remaining_time":0.2615241915},
{"learn":[3.116343362],"iteration":950,"passed_time":4.970115691,"remaining_time":0.2560837738},
{"learn":[3.11480829],"iteration":951,"passed_time":4.997350656,"remaining_time":0.25196726},
{"learn":[3.112607903],"iteration":952,"passed_time":4.998714434,"remaining_time":0.2465263152},
{"learn":[3.111661241],"iteration":953,"passed_time":4.999775809,"remaining_time":0.2410793367},
{"learn":[3.110249676],"iteration":954,"passed_time":5.000735817,"remaining_time":0.2356367662},
{"learn":[3.107333579],"iteration":955,"passed_time":5.00189507,"remaining_time":0.2302127438},
{"learn":[3.107149851],"iteration":956,"passed_time":5.002916086,"remaining_time":0.2247914229},
{"learn":[3.106867336],"iteration":957,"passed_time":5.003869404,"remaining_time":0.2193763204},
{"learn":[3.10364681],"iteration":958,"passed_time":5.005488806,"remaining_time":0.213999},
{"learn":[3.102703811],"iteration":959,"passed_time":5.006503042,"remaining_time":0.2086042934},
{"learn":[3.101469264],"iteration":960,"passed_time":5.00747175,"remaining_time":0.2032168556},
{"learn":[3.09863569],"iteration":961,"passed_time":5.06656678,"remaining_time":0.2001346545},
{"learn":[3.09645939],"iteration":962,"passed_time":5.067755303,"remaining_time":0.1947112629},
{"learn":[3.096240186],"iteration":963,"passed_time":5.068682691,"remaining_time":0.1892869055},
{"learn":[3.094838828],"iteration":964,"passed_time":5.069541931,"remaining_time":0.1838693965},
{"learn":[3.094176802],"iteration":965,"passed_time":5.187240864,"remaining_time":0.182573695},
{"learn":[3.093182279],"iteration":966,"passed_time":5.188160193,"remaining_time":0.1770520024},
{"learn":[3.090150687],"iteration":967,"passed_time":5.188957254,"remaining_time":0.171535777},
{"learn":[3.088612829],"iteration":968,"passed_time":5.189813484,"remaining_time":0.1660311847},
{"learn":[3.087153684],"iteration":969,"passed_time":5.190753522,"remaining_time":0.1605387687},
{"learn":[3.085866843],"iteration":970,"passed_time":5.191574903,"remaining_time":0.1550521856},
{"learn":[3.082669094],"iteration":971,"passed_time":5.192369555,"remaining_time":0.1495744316},
{"learn":[3.081047548],"iteration":972,"passed_time":5.193644295,"remaining_time":0.1441196259},
{"learn":[3.079684322],"iteration":973,"passed_time":5.194933295,"remaining_time":0.138673784},
{"learn":[3.07613431],"iteration":974,"passed_time":5.196198335,"remaining_time":0.1332358547},
{"learn":[3.074005935],"iteration":975,"passed_time":5.197135333,"remaining_time":0.1277984098},
{"learn":[3.072988853],"iteration":976,"passed_time":5.198018673,"remaining_time":0.1223689145},
{"learn":[3.072344268],"iteration":977,"passed_time":5.198821074,"remaining_time":0.1169468953},
{"learn":[3.070654438],"iteration":978,"passed_time":5.199597766,"remaining_time":0.1115337621},
{"learn":[3.069724506],"iteration":979,"passed_time":5.200375008,"remaining_time":0.1061301022},
{"learn":[3.067763166],"iteration":980,"passed_time":5.202118197,"remaining_time":0.1007545828},
{"learn":[3.066737893],"iteration":981,"passed_time":5.203549134,"remaining_time":0.09538073768},
{"learn":[3.065248174],"iteration":982,"passed_time":5.209503795,"remaining_time":0.09009314803},
{"learn":[3.063186837],"iteration":983,"passed_time":5.210733216,"remaining_time":0.08472736937},
{"learn":[3.062880371],"iteration":984,"passed_time":5.211714443,"remaining_time":0.07936620979},
{"learn":[3.061288645],"iteration":985,"passed_time":5.212781808,"remaining_time":0.07401515752},
{"learn":[3.059970575],"iteration":986,"passed_time":5.257080744,"remaining_time":0.06924219825},
{"learn":[3.059576341],"iteration":987,"passed_time":5.258066621,"remaining_time":0.06386315734},
{"learn":[3.058175919],"iteration":988,"passed_time":5.259254554,"remaining_time":0.05849524782},
{"learn":[3.056830702],"iteration":989,"passed_time":5.261424963,"remaining_time":0.0531457067},
{"learn":[3.056336579],"iteration":990,"passed_time":5.262353371,"remaining_time":0.04779130206},
{"learn":[3.055810414],"iteration":991,"passed_time":5.279670927,"remaining_time":0.04257799135},
{"learn":[3.055476518],"iteration":992,"passed_time":5.280702103,"remaining_time":0.03722549317},
{"learn":[3.053331734],"iteration":993,"passed_time":5.281861586,"remaining_time":0.0318824643},
{"learn":[3.050890374],"iteration":994,"passed_time":5.282940791,"remaining_time":0.02654744116},
{"learn":[3.04972623],"iteration":995,"passed_time":5.283961757,"remaining_time":0.02122072995},
{"learn":[3.047217327],"iteration":996,"passed_time":5.285360024,"remaining_time":0.01590379145},
{"learn":[3.047155483],"iteration":997,"passed_time":5.319467418,"remaining_time":0.01066025535},
{"learn":[3.04430671],"iteration":998,"passed_time":5.320786248,"remaining_time":0.00532611236},
{"learn":[3.042664195],"iteration":999,"passed_time":5.32238819,"remaining_time":0}
]}